<CtCheapTimeSolution id="1">
  <id>0</id>
  <timeResolutionInMinutes>5</timeResolutionInMinutes>
  <globalPeriodRangeFrom>0</globalPeriodRangeFrom>
  <globalPeriodRangeTo>288</globalPeriodRangeTo>
  <resourceList id="2">
    <CtResource id="3">
      <id>0</id>
      <index>0</index>
    </CtResource>
    <CtResource id="4">
      <id>1</id>
      <index>1</index>
    </CtResource>
    <CtResource id="5">
      <id>2</id>
      <index>2</index>
    </CtResource>
  </resourceList>
  <machineList id="6">
    <CtMachine id="7">
      <id>0</id>
      <index>0</index>
      <powerConsumptionMicros>12000000000000</powerConsumptionMicros>
      <spinUpDownCostMicros>20000000000</spinUpDownCostMicros>
      <machineCapacityList id="8">
        <CtMachineCapacity id="9">
          <id>0</id>
          <resource reference="3"/>
          <capacity>2565</capacity>
        </CtMachineCapacity>
        <CtMachineCapacity id="10">
          <id>1</id>
          <resource reference="4"/>
          <capacity>2465</capacity>
        </CtMachineCapacity>
        <CtMachineCapacity id="11">
          <id>2</id>
          <resource reference="5"/>
          <capacity>2488</capacity>
        </CtMachineCapacity>
      </machineCapacityList>
    </CtMachine>
    <CtMachine id="12">
      <id>1</id>
      <index>1</index>
      <powerConsumptionMicros>13000000000000</powerConsumptionMicros>
      <spinUpDownCostMicros>10000000000</spinUpDownCostMicros>
      <machineCapacityList id="13">
        <CtMachineCapacity id="14">
          <id>3</id>
          <resource reference="3"/>
          <capacity>2568</capacity>
        </CtMachineCapacity>
        <CtMachineCapacity id="15">
          <id>4</id>
          <resource reference="4"/>
          <capacity>2408</capacity>
        </CtMachineCapacity>
        <CtMachineCapacity id="16">
          <id>5</id>
          <resource reference="5"/>
          <capacity>2498</capacity>
        </CtMachineCapacity>
      </machineCapacityList>
    </CtMachine>
  </machineList>
  <taskList id="17">
    <CtTask id="18">
      <id>0</id>
      <powerConsumptionMicros>5617000000000</powerConsumptionMicros>
      <duration>171</duration>
      <startPeriodRangeFrom>5</startPeriodRangeFrom>
      <startPeriodRangeTo>107</startPeriodRangeTo>
      <taskRequirementList id="19">
        <CtTaskRequirement id="20">
          <id>0</id>
          <resource reference="3"/>
          <resourceUsage>91</resourceUsage>
        </CtTaskRequirement>
        <CtTaskRequirement id="21">
          <id>1</id>
          <resource reference="4"/>
          <resourceUsage>267</resourceUsage>
        </CtTaskRequirement>
        <CtTaskRequirement id="22">
          <id>2</id>
          <resource reference="5"/>
          <resourceUsage>317</resourceUsage>
        </CtTaskRequirement>
      </taskRequirementList>
    </CtTask>
    <CtTask id="23">
      <id>1</id>
      <powerConsumptionMicros>1592000000000</powerConsumptionMicros>
      <duration>18</duration>
      <startPeriodRangeFrom>2</startPeriodRangeFrom>
      <startPeriodRangeTo>205</startPeriodRangeTo>
      <taskRequirementList id="24">
        <CtTaskRequirement id="25">
          <id>3</id>
          <resource reference="3"/>
          <resourceUsage>51</resourceUsage>
        </CtTaskRequirement>
        <CtTaskRequirement id="26">
          <id>4</id>
          <resource reference="4"/>
          <resourceUsage>10</resourceUsage>
        </CtTaskRequirement>
        <CtTaskRequirement id="27">
          <id>5</id>
          <resource reference="5"/>
          <resourceUsage>12</resourceUsage>
        </CtTaskRequirement>
      </taskRequirementList>
    </CtTask>
    <CtTask id="28">
      <id>2</id>
      <powerConsumptionMicros>52357000000000</powerConsumptionMicros>
      <duration>3</duration>
      <startPeriodRangeFrom>6</startPeriodRangeFrom>
      <startPeriodRangeTo>43</startPeriodRangeTo>
      <taskRequirementList id="29">
        <CtTaskRequirement id="30">
          <id>6</id>
          <resource reference="3"/>
          <resourceUsage>1689</resourceUsage>
        </CtTaskRequirement>
        <CtTaskRequirement id="31">
          <id>7</id>
          <resource reference="4"/>
          <resourceUsage>328</resourceUsage>
        </CtTaskRequirement>
        <CtTaskRequirement id="32">
          <id>8</id>
          <resource reference="5"/>
          <resourceUsage>310</resourceUsage>
        </CtTaskRequirement>
      </taskRequirementList>
    </CtTask>
    <CtTask id="33">
      <id>3</id>
      <powerConsumptionMicros>25173000000000</powerConsumptionMicros>
      <duration>189</duration>
      <startPeriodRangeFrom>25</startPeriodRangeFrom>
      <startPeriodRangeTo>100</startPeriodRangeTo>
      <taskRequirementList id="34">
        <CtTaskRequirement id="35">
          <id>9</id>
          <resource reference="3"/>
          <resourceUsage>374</resourceUsage>
        </CtTaskRequirement>
        <CtTaskRequirement id="36">
          <id>10</id>
          <resource reference="4"/>
          <resourceUsage>1824</resourceUsage>
        </CtTaskRequirement>
        <CtTaskRequirement id="37">
          <id>11</id>
          <resource reference="5"/>
          <resourceUsage>716</resourceUsage>
        </CtTaskRequirement>
      </taskRequirementList>
    </CtTask>
    <CtTask id="38">
      <id>4</id>
      <powerConsumptionMicros>19697000000000</powerConsumptionMicros>
      <duration>177</duration>
      <startPeriodRangeFrom>29</startPeriodRangeFrom>
      <startPeriodRangeTo>111</startPeriodRangeTo>
      <taskRequirementList id="39">
        <CtTaskRequirement id="40">
          <id>12</id>
          <resource reference="3"/>
          <resourceUsage>639</resourceUsage>
        </CtTaskRequirement>
        <CtTaskRequirement id="41">
          <id>13</id>
          <resource reference="4"/>
          <resourceUsage>113</resourceUsage>
        </CtTaskRequirement>
        <CtTaskRequirement id="42">
          <id>14</id>
          <resource reference="5"/>
          <resourceUsage>107</resourceUsage>
        </CtTaskRequirement>
      </taskRequirementList>
    </CtTask>
    <CtTask id="43">
      <id>5</id>
      <powerConsumptionMicros>10828000000000</powerConsumptionMicros>
      <duration>201</duration>
      <startPeriodRangeFrom>85</startPeriodRangeFrom>
      <startPeriodRangeTo>88</startPeriodRangeTo>
      <taskRequirementList id="44">
        <CtTaskRequirement id="45">
          <id>15</id>
          <resource reference="3"/>
          <resourceUsage>190</resourceUsage>
        </CtTaskRequirement>
        <CtTaskRequirement id="46">
          <id>16</id>
          <resource reference="4"/>
          <resourceUsage>194</resourceUsage>
        </CtTaskRequirement>
        <CtTaskRequirement id="47">
          <id>17</id>
          <resource reference="5"/>
          <resourceUsage>990</resourceUsage>
        </CtTaskRequirement>
      </taskRequirementList>
    </CtTask>
    <CtTask id="48">
      <id>6</id>
      <powerConsumptionMicros>51026000000000</powerConsumptionMicros>
      <duration>18</duration>
      <startPeriodRangeFrom>2</startPeriodRangeFrom>
      <startPeriodRangeTo>88</startPeriodRangeTo>
      <taskRequirementList id="49">
        <CtTaskRequirement id="50">
          <id>18</id>
          <resource reference="3"/>
          <resourceUsage>1652</resourceUsage>
        </CtTaskRequirement>
        <CtTaskRequirement id="51">
          <id>19</id>
          <resource reference="4"/>
          <resourceUsage>302</resourceUsage>
        </CtTaskRequirement>
        <CtTaskRequirement id="52">
          <id>20</id>
          <resource reference="5"/>
          <resourceUsage>287</resourceUsage>
        </CtTaskRequirement>
      </taskRequirementList>
    </CtTask>
    <CtTask id="53">
      <id>7</id>
      <powerConsumptionMicros>67548000000000</powerConsumptionMicros>
      <duration>10</duration>
      <startPeriodRangeFrom>1</startPeriodRangeFrom>
      <startPeriodRangeTo>155</startPeriodRangeTo>
      <taskRequirementList id="54">
        <CtTaskRequirement id="55">
          <id>21</id>
          <resource reference="3"/>
          <resourceUsage>1887</resourceUsage>
        </CtTaskRequirement>
        <CtTaskRequirement id="56">
          <id>22</id>
          <resource reference="4"/>
          <resourceUsage>1636</resourceUsage>
        </CtTaskRequirement>
        <CtTaskRequirement id="57">
          <id>23</id>
          <resource reference="5"/>
          <resourceUsage>625</resourceUsage>
        </CtTaskRequirement>
      </taskRequirementList>
    </CtTask>
    <CtTask id="58">
      <id>8</id>
      <powerConsumptionMicros>19446000000000</powerConsumptionMicros>
      <duration>11</duration>
      <startPeriodRangeFrom>0</startPeriodRangeFrom>
      <startPeriodRangeTo>22</startPeriodRangeTo>
      <taskRequirementList id="59">
        <CtTaskRequirement id="60">
          <id>24</id>
          <resource reference="3"/>
          <resourceUsage>303</resourceUsage>
        </CtTaskRequirement>
        <CtTaskRequirement id="61">
          <id>25</id>
          <resource reference="4"/>
          <resourceUsage>502</resourceUsage>
        </CtTaskRequirement>
        <CtTaskRequirement id="62">
          <id>26</id>
          <resource reference="5"/>
          <resourceUsage>1815</resourceUsage>
        </CtTaskRequirement>
      </taskRequirementList>
    </CtTask>
    <CtTask id="63">
      <id>9</id>
      <powerConsumptionMicros>12970000000000</powerConsumptionMicros>
      <duration>60</duration>
      <startPeriodRangeFrom>25</startPeriodRangeFrom>
      <startPeriodRangeTo>39</startPeriodRangeTo>
      <taskRequirementList id="64">
        <CtTaskRequirement id="65">
          <id>27</id>
          <resource reference="3"/>
          <resourceUsage>221</resourceUsage>
        </CtTaskRequirement>
        <CtTaskRequirement id="66">
          <id>28</id>
          <resource reference="4"/>
          <resourceUsage>237</resourceUsage>
        </CtTaskRequirement>
        <CtTaskRequirement id="67">
          <id>29</id>
          <resource reference="5"/>
          <resourceUsage>1225</resourceUsage>
        </CtTaskRequirement>
      </taskRequirementList>
    </CtTask>
    <CtTask id="68">
      <id>10</id>
      <powerConsumptionMicros>10345000000000</powerConsumptionMicros>
      <duration>27</duration>
      <startPeriodRangeFrom>2</startPeriodRangeFrom>
      <startPeriodRangeTo>134</startPeriodRangeTo>
      <taskRequirementList id="69">
        <CtTaskRequirement id="70">
          <id>30</id>
          <resource reference="3"/>
          <resourceUsage>168</resourceUsage>
        </CtTaskRequirement>
        <CtTaskRequirement id="71">
          <id>31</id>
          <resource reference="4"/>
          <resourceUsage>171</resourceUsage>
        </CtTaskRequirement>
        <CtTaskRequirement id="72">
          <id>32</id>
          <resource reference="5"/>
          <resourceUsage>1062</resourceUsage>
        </CtTaskRequirement>
      </taskRequirementList>
    </CtTask>
    <CtTask id="73">
      <id>11</id>
      <powerConsumptionMicros>34218000000000</powerConsumptionMicros>
      <duration>199</duration>
      <startPeriodRangeFrom>9</startPeriodRangeFrom>
      <startPeriodRangeTo>88</startPeriodRangeTo>
      <taskRequirementList id="74">
        <CtTaskRequirement id="75">
          <id>33</id>
          <resource reference="3"/>
          <resourceUsage>792</resourceUsage>
        </CtTaskRequirement>
        <CtTaskRequirement id="76">
          <id>34</id>
          <resource reference="4"/>
          <resourceUsage>1548</resourceUsage>
        </CtTaskRequirement>
        <CtTaskRequirement id="77">
          <id>35</id>
          <resource reference="5"/>
          <resourceUsage>385</resourceUsage>
        </CtTaskRequirement>
      </taskRequirementList>
    </CtTask>
    <CtTask id="78">
      <id>12</id>
      <powerConsumptionMicros>36409000000000</powerConsumptionMicros>
      <duration>196</duration>
      <startPeriodRangeFrom>8</startPeriodRangeFrom>
      <startPeriodRangeTo>45</startPeriodRangeTo>
      <taskRequirementList id="79">
        <CtTaskRequirement id="80">
          <id>36</id>
          <resource reference="3"/>
          <resourceUsage>1190</resourceUsage>
        </CtTaskRequirement>
        <CtTaskRequirement id="81">
          <id>37</id>
          <resource reference="4"/>
          <resourceUsage>171</resourceUsage>
        </CtTaskRequirement>
        <CtTaskRequirement id="82">
          <id>38</id>
          <resource reference="5"/>
          <resourceUsage>193</resourceUsage>
        </CtTaskRequirement>
      </taskRequirementList>
    </CtTask>
    <CtTask id="83">
      <id>13</id>
      <powerConsumptionMicros>3929000000000</powerConsumptionMicros>
      <duration>169</duration>
      <startPeriodRangeFrom>14</startPeriodRangeFrom>
      <startPeriodRangeTo>105</startPeriodRangeTo>
      <taskRequirementList id="84">
        <CtTaskRequirement id="85">
          <id>39</id>
          <resource reference="3"/>
          <resourceUsage>73</resourceUsage>
        </CtTaskRequirement>
        <CtTaskRequirement id="86">
          <id>40</id>
          <resource reference="4"/>
          <resourceUsage>73</resourceUsage>
        </CtTaskRequirement>
        <CtTaskRequirement id="87">
          <id>41</id>
          <resource reference="5"/>
          <resourceUsage>327</resourceUsage>
        </CtTaskRequirement>
      </taskRequirementList>
    </CtTask>
    <CtTask id="88">
      <id>14</id>
      <powerConsumptionMicros>3790000000000</powerConsumptionMicros>
      <duration>36</duration>
      <startPeriodRangeFrom>67</startPeriodRangeFrom>
      <startPeriodRangeTo>253</startPeriodRangeTo>
      <taskRequirementList id="89">
        <CtTaskRequirement id="90">
          <id>42</id>
          <resource reference="3"/>
          <resourceUsage>67</resourceUsage>
        </CtTaskRequirement>
        <CtTaskRequirement id="91">
          <id>43</id>
          <resource reference="4"/>
          <resourceUsage>68</resourceUsage>
        </CtTaskRequirement>
        <CtTaskRequirement id="92">
          <id>44</id>
          <resource reference="5"/>
          <resourceUsage>343</resourceUsage>
        </CtTaskRequirement>
      </taskRequirementList>
    </CtTask>
    <CtTask id="93">
      <id>15</id>
      <powerConsumptionMicros>38290000000000</powerConsumptionMicros>
      <duration>23</duration>
      <startPeriodRangeFrom>0</startPeriodRangeFrom>
      <startPeriodRangeTo>50</startPeriodRangeTo>
      <taskRequirementList id="94">
        <CtTaskRequirement id="95">
          <id>45</id>
          <resource reference="3"/>
          <resourceUsage>611</resourceUsage>
        </CtTaskRequirement>
        <CtTaskRequirement id="96">
          <id>46</id>
          <resource reference="4"/>
          <resourceUsage>2004</resourceUsage>
        </CtTaskRequirement>
        <CtTaskRequirement id="97">
          <id>47</id>
          <resource reference="5"/>
          <resourceUsage>1950</resourceUsage>
        </CtTaskRequirement>
      </taskRequirementList>
    </CtTask>
    <CtTask id="98">
      <id>16</id>
      <powerConsumptionMicros>19560000000000</powerConsumptionMicros>
      <duration>52</duration>
      <startPeriodRangeFrom>20</startPeriodRangeFrom>
      <startPeriodRangeTo>97</startPeriodRangeTo>
      <taskRequirementList id="99">
        <CtTaskRequirement id="100">
          <id>48</id>
          <resource reference="3"/>
          <resourceUsage>633</resourceUsage>
        </CtTaskRequirement>
        <CtTaskRequirement id="101">
          <id>49</id>
          <resource reference="4"/>
          <resourceUsage>115</resourceUsage>
        </CtTaskRequirement>
        <CtTaskRequirement id="102">
          <id>50</id>
          <resource reference="5"/>
          <resourceUsage>113</resourceUsage>
        </CtTaskRequirement>
      </taskRequirementList>
    </CtTask>
    <CtTask id="103">
      <id>17</id>
      <powerConsumptionMicros>1713000000000</powerConsumptionMicros>
      <duration>3</duration>
      <startPeriodRangeFrom>13</startPeriodRangeFrom>
      <startPeriodRangeTo>108</startPeriodRangeTo>
      <taskRequirementList id="104">
        <CtTaskRequirement id="105">
          <id>51</id>
          <resource reference="3"/>
          <resourceUsage>55</resourceUsage>
        </CtTaskRequirement>
        <CtTaskRequirement id="106">
          <id>52</id>
          <resource reference="4"/>
          <resourceUsage>12</resourceUsage>
        </CtTaskRequirement>
        <CtTaskRequirement id="107">
          <id>53</id>
          <resource reference="5"/>
          <resourceUsage>10</resourceUsage>
        </CtTaskRequirement>
      </taskRequirementList>
    </CtTask>
    <CtTask id="108">
      <id>18</id>
      <powerConsumptionMicros>23261000000000</powerConsumptionMicros>
      <duration>63</duration>
      <startPeriodRangeFrom>25</startPeriodRangeFrom>
      <startPeriodRangeTo>80</startPeriodRangeTo>
      <taskRequirementList id="109">
        <CtTaskRequirement id="110">
          <id>54</id>
          <resource reference="3"/>
          <resourceUsage>364</resourceUsage>
        </CtTaskRequirement>
        <CtTaskRequirement id="111">
          <id>55</id>
          <resource reference="4"/>
          <resourceUsage>1608</resourceUsage>
        </CtTaskRequirement>
        <CtTaskRequirement id="112">
          <id>56</id>
          <resource reference="5"/>
          <resourceUsage>649</resourceUsage>
        </CtTaskRequirement>
      </taskRequirementList>
    </CtTask>
    <CtTask id="113">
      <id>19</id>
      <powerConsumptionMicros>32381000000000</powerConsumptionMicros>
      <duration>185</duration>
      <startPeriodRangeFrom>4</startPeriodRangeFrom>
      <startPeriodRangeTo>104</startPeriodRangeTo>
      <taskRequirementList id="114">
        <CtTaskRequirement id="115">
          <id>57</id>
          <resource reference="3"/>
          <resourceUsage>1041</resourceUsage>
        </CtTaskRequirement>
        <CtTaskRequirement id="116">
          <id>58</id>
          <resource reference="4"/>
          <resourceUsage>218</resourceUsage>
        </CtTaskRequirement>
        <CtTaskRequirement id="117">
          <id>59</id>
          <resource reference="5"/>
          <resourceUsage>194</resourceUsage>
        </CtTaskRequirement>
      </taskRequirementList>
    </CtTask>
    <CtTask id="118">
      <id>20</id>
      <powerConsumptionMicros>35366000000000</powerConsumptionMicros>
      <duration>57</duration>
      <startPeriodRangeFrom>4</startPeriodRangeFrom>
      <startPeriodRangeTo>80</startPeriodRangeTo>
      <taskRequirementList id="119">
        <CtTaskRequirement id="120">
          <id>60</id>
          <resource reference="3"/>
          <resourceUsage>1143</resourceUsage>
        </CtTaskRequirement>
        <CtTaskRequirement id="121">
          <id>61</id>
          <resource reference="4"/>
          <resourceUsage>220</resourceUsage>
        </CtTaskRequirement>
        <CtTaskRequirement id="122">
          <id>62</id>
          <resource reference="5"/>
          <resourceUsage>197</resourceUsage>
        </CtTaskRequirement>
      </taskRequirementList>
    </CtTask>
    <CtTask id="123">
      <id>21</id>
      <powerConsumptionMicros>13472000000000</powerConsumptionMicros>
      <duration>185</duration>
      <startPeriodRangeFrom>44</startPeriodRangeFrom>
      <startPeriodRangeTo>103</startPeriodRangeTo>
      <taskRequirementList id="124">
        <CtTaskRequirement id="125">
          <id>63</id>
          <resource reference="3"/>
          <resourceUsage>233</resourceUsage>
        </CtTaskRequirement>
        <CtTaskRequirement id="126">
          <id>64</id>
          <resource reference="4"/>
          <resourceUsage>235</resourceUsage>
        </CtTaskRequirement>
        <CtTaskRequirement id="127">
          <id>65</id>
          <resource reference="5"/>
          <resourceUsage>1265</resourceUsage>
        </CtTaskRequirement>
      </taskRequirementList>
    </CtTask>
    <CtTask id="128">
      <id>22</id>
      <powerConsumptionMicros>31916000000000</powerConsumptionMicros>
      <duration>71</duration>
      <startPeriodRangeFrom>1</startPeriodRangeFrom>
      <startPeriodRangeTo>218</startPeriodRangeTo>
      <taskRequirementList id="129">
        <CtTaskRequirement id="130">
          <id>66</id>
          <resource reference="3"/>
          <resourceUsage>1037</resourceUsage>
        </CtTaskRequirement>
        <CtTaskRequirement id="131">
          <id>67</id>
          <resource reference="4"/>
          <resourceUsage>170</resourceUsage>
        </CtTaskRequirement>
        <CtTaskRequirement id="132">
          <id>68</id>
          <resource reference="5"/>
          <resourceUsage>182</resourceUsage>
        </CtTaskRequirement>
      </taskRequirementList>
    </CtTask>
    <CtTask id="133">
      <id>23</id>
      <powerConsumptionMicros>36293000000000</powerConsumptionMicros>
      <duration>73</duration>
      <startPeriodRangeFrom>139</startPeriodRangeFrom>
      <startPeriodRangeTo>216</startPeriodRangeTo>
      <taskRequirementList id="134">
        <CtTaskRequirement id="135">
          <id>69</id>
          <resource reference="3"/>
          <resourceUsage>854</resourceUsage>
        </CtTaskRequirement>
        <CtTaskRequirement id="136">
          <id>70</id>
          <resource reference="4"/>
          <resourceUsage>1573</resourceUsage>
        </CtTaskRequirement>
        <CtTaskRequirement id="137">
          <id>71</id>
          <resource reference="5"/>
          <resourceUsage>414</resourceUsage>
        </CtTaskRequirement>
      </taskRequirementList>
    </CtTask>
    <CtTask id="138">
      <id>24</id>
      <powerConsumptionMicros>8860000000000</powerConsumptionMicros>
      <duration>25</duration>
      <startPeriodRangeFrom>11</startPeriodRangeFrom>
      <startPeriodRangeTo>83</startPeriodRangeTo>
      <taskRequirementList id="139">
        <CtTaskRequirement id="140">
          <id>72</id>
          <resource reference="3"/>
          <resourceUsage>137</resourceUsage>
        </CtTaskRequirement>
        <CtTaskRequirement id="141">
          <id>73</id>
          <resource reference="4"/>
          <resourceUsage>357</resourceUsage>
        </CtTaskRequirement>
        <CtTaskRequirement id="142">
          <id>74</id>
          <resource reference="5"/>
          <resourceUsage>642</resourceUsage>
        </CtTaskRequirement>
      </taskRequirementList>
    </CtTask>
  </taskList>
  <periodList id="143">
    <CtPeriod id="144">
      <id>0</id>
      <index>0</index>
      <powerPriceMicros>405833333</powerPriceMicros>
    </CtPeriod>
    <CtPeriod id="145">
      <id>1</id>
      <index>1</index>
      <powerPriceMicros>405833333</powerPriceMicros>
    </CtPeriod>
    <CtPeriod id="146">
      <id>2</id>
      <index>2</index>
      <powerPriceMicros>405833333</powerPriceMicros>
    </CtPeriod>
    <CtPeriod id="147">
      <id>3</id>
      <index>3</index>
      <powerPriceMicros>405833333</powerPriceMicros>
    </CtPeriod>
    <CtPeriod id="148">
      <id>4</id>
      <index>4</index>
      <powerPriceMicros>405833333</powerPriceMicros>
    </CtPeriod>
    <CtPeriod id="149">
      <id>5</id>
      <index>5</index>
      <powerPriceMicros>405833333</powerPriceMicros>
    </CtPeriod>
    <CtPeriod id="150">
      <id>6</id>
      <index>6</index>
      <powerPriceMicros>399416667</powerPriceMicros>
    </CtPeriod>
    <CtPeriod id="151">
      <id>7</id>
      <index>7</index>
      <powerPriceMicros>399416667</powerPriceMicros>
    </CtPeriod>
    <CtPeriod id="152">
      <id>8</id>
      <index>8</index>
      <powerPriceMicros>399416667</powerPriceMicros>
    </CtPeriod>
    <CtPeriod id="153">
      <id>9</id>
      <index>9</index>
      <powerPriceMicros>399416667</powerPriceMicros>
    </CtPeriod>
    <CtPeriod id="154">
      <id>10</id>
      <index>10</index>
      <powerPriceMicros>399416667</powerPriceMicros>
    </CtPeriod>
    <CtPeriod id="155">
      <id>11</id>
      <index>11</index>
      <powerPriceMicros>399416667</powerPriceMicros>
    </CtPeriod>
    <CtPeriod id="156">
      <id>12</id>
      <index>12</index>
      <powerPriceMicros>399416667</powerPriceMicros>
    </CtPeriod>
    <CtPeriod id="157">
      <id>13</id>
      <index>13</index>
      <powerPriceMicros>399416667</powerPriceMicros>
    </CtPeriod>
    <CtPeriod id="158">
      <id>14</id>
      <index>14</index>
      <powerPriceMicros>399416667</powerPriceMicros>
    </CtPeriod>
    <CtPeriod id="159">
      <id>15</id>
      <index>15</index>
      <powerPriceMicros>399416667</powerPriceMicros>
    </CtPeriod>
    <CtPeriod id="160">
      <id>16</id>
      <index>16</index>
      <powerPriceMicros>399416667</powerPriceMicros>
    </CtPeriod>
    <CtPeriod id="161">
      <id>17</id>
      <index>17</index>
      <powerPriceMicros>399416667</powerPriceMicros>
    </CtPeriod>
    <CtPeriod id="162">
      <id>18</id>
      <index>18</index>
      <powerPriceMicros>396000000</powerPriceMicros>
    </CtPeriod>
    <CtPeriod id="163">
      <id>19</id>
      <index>19</index>
      <powerPriceMicros>396000000</powerPriceMicros>
    </CtPeriod>
    <CtPeriod id="164">
      <id>20</id>
      <index>20</index>
      <powerPriceMicros>396000000</powerPriceMicros>
    </CtPeriod>
    <CtPeriod id="165">
      <id>21</id>
      <index>21</index>
      <powerPriceMicros>396000000</powerPriceMicros>
    </CtPeriod>
    <CtPeriod id="166">
      <id>22</id>
      <index>22</index>
      <powerPriceMicros>396000000</powerPriceMicros>
    </CtPeriod>
    <CtPeriod id="167">
      <id>23</id>
      <index>23</index>
      <powerPriceMicros>396000000</powerPriceMicros>
    </CtPeriod>
    <CtPeriod id="168">
      <id>24</id>
      <index>24</index>
      <powerPriceMicros>396000000</powerPriceMicros>
    </CtPeriod>
    <CtPeriod id="169">
      <id>25</id>
      <index>25</index>
      <powerPriceMicros>396000000</powerPriceMicros>
    </CtPeriod>
    <CtPeriod id="170">
      <id>26</id>
      <index>26</index>
      <powerPriceMicros>396000000</powerPriceMicros>
    </CtPeriod>
    <CtPeriod id="171">
      <id>27</id>
      <index>27</index>
      <powerPriceMicros>396000000</powerPriceMicros>
    </CtPeriod>
    <CtPeriod id="172">
      <id>28</id>
      <index>28</index>
      <powerPriceMicros>396000000</powerPriceMicros>
    </CtPeriod>
    <CtPeriod id="173">
      <id>29</id>
      <index>29</index>
      <powerPriceMicros>396000000</powerPriceMicros>
    </CtPeriod>
    <CtPeriod id="174">
      <id>30</id>
      <index>30</index>
      <powerPriceMicros>366666667</powerPriceMicros>
    </CtPeriod>
    <CtPeriod id="175">
      <id>31</id>
      <index>31</index>
      <powerPriceMicros>366666667</powerPriceMicros>
    </CtPeriod>
    <CtPeriod id="176">
      <id>32</id>
      <index>32</index>
      <powerPriceMicros>366666667</powerPriceMicros>
    </CtPeriod>
    <CtPeriod id="177">
      <id>33</id>
      <index>33</index>
      <powerPriceMicros>366666667</powerPriceMicros>
    </CtPeriod>
    <CtPeriod id="178">
      <id>34</id>
      <index>34</index>
      <powerPriceMicros>366666667</powerPriceMicros>
    </CtPeriod>
    <CtPeriod id="179">
      <id>35</id>
      <index>35</index>
      <powerPriceMicros>366666667</powerPriceMicros>
    </CtPeriod>
    <CtPeriod id="180">
      <id>36</id>
      <index>36</index>
      <powerPriceMicros>396000000</powerPriceMicros>
    </CtPeriod>
    <CtPeriod id="181">
      <id>37</id>
      <index>37</index>
      <powerPriceMicros>396000000</powerPriceMicros>
    </CtPeriod>
    <CtPeriod id="182">
      <id>38</id>
      <index>38</index>
      <powerPriceMicros>396000000</powerPriceMicros>
    </CtPeriod>
    <CtPeriod id="183">
      <id>39</id>
      <index>39</index>
      <powerPriceMicros>396000000</powerPriceMicros>
    </CtPeriod>
    <CtPeriod id="184">
      <id>40</id>
      <index>40</index>
      <powerPriceMicros>396000000</powerPriceMicros>
    </CtPeriod>
    <CtPeriod id="185">
      <id>41</id>
      <index>41</index>
      <powerPriceMicros>396000000</powerPriceMicros>
    </CtPeriod>
    <CtPeriod id="186">
      <id>42</id>
      <index>42</index>
      <powerPriceMicros>396000000</powerPriceMicros>
    </CtPeriod>
    <CtPeriod id="187">
      <id>43</id>
      <index>43</index>
      <powerPriceMicros>396000000</powerPriceMicros>
    </CtPeriod>
    <CtPeriod id="188">
      <id>44</id>
      <index>44</index>
      <powerPriceMicros>396000000</powerPriceMicros>
    </CtPeriod>
    <CtPeriod id="189">
      <id>45</id>
      <index>45</index>
      <powerPriceMicros>396000000</powerPriceMicros>
    </CtPeriod>
    <CtPeriod id="190">
      <id>46</id>
      <index>46</index>
      <powerPriceMicros>396000000</powerPriceMicros>
    </CtPeriod>
    <CtPeriod id="191">
      <id>47</id>
      <index>47</index>
      <powerPriceMicros>396000000</powerPriceMicros>
    </CtPeriod>
    <CtPeriod id="192">
      <id>48</id>
      <index>48</index>
      <powerPriceMicros>341833333</powerPriceMicros>
    </CtPeriod>
    <CtPeriod id="193">
      <id>49</id>
      <index>49</index>
      <powerPriceMicros>341833333</powerPriceMicros>
    </CtPeriod>
    <CtPeriod id="194">
      <id>50</id>
      <index>50</index>
      <powerPriceMicros>341833333</powerPriceMicros>
    </CtPeriod>
    <CtPeriod id="195">
      <id>51</id>
      <index>51</index>
      <powerPriceMicros>341833333</powerPriceMicros>
    </CtPeriod>
    <CtPeriod id="196">
      <id>52</id>
      <index>52</index>
      <powerPriceMicros>341833333</powerPriceMicros>
    </CtPeriod>
    <CtPeriod id="197">
      <id>53</id>
      <index>53</index>
      <powerPriceMicros>341833333</powerPriceMicros>
    </CtPeriod>
    <CtPeriod id="198">
      <id>54</id>
      <index>54</index>
      <powerPriceMicros>341666667</powerPriceMicros>
    </CtPeriod>
    <CtPeriod id="199">
      <id>55</id>
      <index>55</index>
      <powerPriceMicros>341666667</powerPriceMicros>
    </CtPeriod>
    <CtPeriod id="200">
      <id>56</id>
      <index>56</index>
      <powerPriceMicros>341666667</powerPriceMicros>
    </CtPeriod>
    <CtPeriod id="201">
      <id>57</id>
      <index>57</index>
      <powerPriceMicros>341666667</powerPriceMicros>
    </CtPeriod>
    <CtPeriod id="202">
      <id>58</id>
      <index>58</index>
      <powerPriceMicros>341666667</powerPriceMicros>
    </CtPeriod>
    <CtPeriod id="203">
      <id>59</id>
      <index>59</index>
      <powerPriceMicros>341666667</powerPriceMicros>
    </CtPeriod>
    <CtPeriod id="204">
      <id>60</id>
      <index>60</index>
      <powerPriceMicros>288416667</powerPriceMicros>
    </CtPeriod>
    <CtPeriod id="205">
      <id>61</id>
      <index>61</index>
      <powerPriceMicros>288416667</powerPriceMicros>
    </CtPeriod>
    <CtPeriod id="206">
      <id>62</id>
      <index>62</index>
      <powerPriceMicros>288416667</powerPriceMicros>
    </CtPeriod>
    <CtPeriod id="207">
      <id>63</id>
      <index>63</index>
      <powerPriceMicros>288416667</powerPriceMicros>
    </CtPeriod>
    <CtPeriod id="208">
      <id>64</id>
      <index>64</index>
      <powerPriceMicros>288416667</powerPriceMicros>
    </CtPeriod>
    <CtPeriod id="209">
      <id>65</id>
      <index>65</index>
      <powerPriceMicros>288416667</powerPriceMicros>
    </CtPeriod>
    <CtPeriod id="210">
      <id>66</id>
      <index>66</index>
      <powerPriceMicros>288416667</powerPriceMicros>
    </CtPeriod>
    <CtPeriod id="211">
      <id>67</id>
      <index>67</index>
      <powerPriceMicros>288416667</powerPriceMicros>
    </CtPeriod>
    <CtPeriod id="212">
      <id>68</id>
      <index>68</index>
      <powerPriceMicros>288416667</powerPriceMicros>
    </CtPeriod>
    <CtPeriod id="213">
      <id>69</id>
      <index>69</index>
      <powerPriceMicros>288416667</powerPriceMicros>
    </CtPeriod>
    <CtPeriod id="214">
      <id>70</id>
      <index>70</index>
      <powerPriceMicros>288416667</powerPriceMicros>
    </CtPeriod>
    <CtPeriod id="215">
      <id>71</id>
      <index>71</index>
      <powerPriceMicros>288416667</powerPriceMicros>
    </CtPeriod>
    <CtPeriod id="216">
      <id>72</id>
      <index>72</index>
      <powerPriceMicros>261583333</powerPriceMicros>
    </CtPeriod>
    <CtPeriod id="217">
      <id>73</id>
      <index>73</index>
      <powerPriceMicros>261583333</powerPriceMicros>
    </CtPeriod>
    <CtPeriod id="218">
      <id>74</id>
      <index>74</index>
      <powerPriceMicros>261583333</powerPriceMicros>
    </CtPeriod>
    <CtPeriod id="219">
      <id>75</id>
      <index>75</index>
      <powerPriceMicros>261583333</powerPriceMicros>
    </CtPeriod>
    <CtPeriod id="220">
      <id>76</id>
      <index>76</index>
      <powerPriceMicros>261583333</powerPriceMicros>
    </CtPeriod>
    <CtPeriod id="221">
      <id>77</id>
      <index>77</index>
      <powerPriceMicros>261583333</powerPriceMicros>
    </CtPeriod>
    <CtPeriod id="222">
      <id>78</id>
      <index>78</index>
      <powerPriceMicros>338666667</powerPriceMicros>
    </CtPeriod>
    <CtPeriod id="223">
      <id>79</id>
      <index>79</index>
      <powerPriceMicros>338666667</powerPriceMicros>
    </CtPeriod>
    <CtPeriod id="224">
      <id>80</id>
      <index>80</index>
      <powerPriceMicros>338666667</powerPriceMicros>
    </CtPeriod>
    <CtPeriod id="225">
      <id>81</id>
      <index>81</index>
      <powerPriceMicros>338666667</powerPriceMicros>
    </CtPeriod>
    <CtPeriod id="226">
      <id>82</id>
      <index>82</index>
      <powerPriceMicros>338666667</powerPriceMicros>
    </CtPeriod>
    <CtPeriod id="227">
      <id>83</id>
      <index>83</index>
      <powerPriceMicros>338666667</powerPriceMicros>
    </CtPeriod>
    <CtPeriod id="228">
      <id>84</id>
      <index>84</index>
      <powerPriceMicros>341750000</powerPriceMicros>
    </CtPeriod>
    <CtPeriod id="229">
      <id>85</id>
      <index>85</index>
      <powerPriceMicros>341750000</powerPriceMicros>
    </CtPeriod>
    <CtPeriod id="230">
      <id>86</id>
      <index>86</index>
      <powerPriceMicros>341750000</powerPriceMicros>
    </CtPeriod>
    <CtPeriod id="231">
      <id>87</id>
      <index>87</index>
      <powerPriceMicros>341750000</powerPriceMicros>
    </CtPeriod>
    <CtPeriod id="232">
      <id>88</id>
      <index>88</index>
      <powerPriceMicros>341750000</powerPriceMicros>
    </CtPeriod>
    <CtPeriod id="233">
      <id>89</id>
      <index>89</index>
      <powerPriceMicros>341750000</powerPriceMicros>
    </CtPeriod>
    <CtPeriod id="234">
      <id>90</id>
      <index>90</index>
      <powerPriceMicros>398000000</powerPriceMicros>
    </CtPeriod>
    <CtPeriod id="235">
      <id>91</id>
      <index>91</index>
      <powerPriceMicros>398000000</powerPriceMicros>
    </CtPeriod>
    <CtPeriod id="236">
      <id>92</id>
      <index>92</index>
      <powerPriceMicros>398000000</powerPriceMicros>
    </CtPeriod>
    <CtPeriod id="237">
      <id>93</id>
      <index>93</index>
      <powerPriceMicros>398000000</powerPriceMicros>
    </CtPeriod>
    <CtPeriod id="238">
      <id>94</id>
      <index>94</index>
      <powerPriceMicros>398000000</powerPriceMicros>
    </CtPeriod>
    <CtPeriod id="239">
      <id>95</id>
      <index>95</index>
      <powerPriceMicros>398000000</powerPriceMicros>
    </CtPeriod>
    <CtPeriod id="240">
      <id>96</id>
      <index>96</index>
      <powerPriceMicros>398000000</powerPriceMicros>
    </CtPeriod>
    <CtPeriod id="241">
      <id>97</id>
      <index>97</index>
      <powerPriceMicros>398000000</powerPriceMicros>
    </CtPeriod>
    <CtPeriod id="242">
      <id>98</id>
      <index>98</index>
      <powerPriceMicros>398000000</powerPriceMicros>
    </CtPeriod>
    <CtPeriod id="243">
      <id>99</id>
      <index>99</index>
      <powerPriceMicros>398000000</powerPriceMicros>
    </CtPeriod>
    <CtPeriod id="244">
      <id>100</id>
      <index>100</index>
      <powerPriceMicros>398000000</powerPriceMicros>
    </CtPeriod>
    <CtPeriod id="245">
      <id>101</id>
      <index>101</index>
      <powerPriceMicros>398000000</powerPriceMicros>
    </CtPeriod>
    <CtPeriod id="246">
      <id>102</id>
      <index>102</index>
      <powerPriceMicros>397833333</powerPriceMicros>
    </CtPeriod>
    <CtPeriod id="247">
      <id>103</id>
      <index>103</index>
      <powerPriceMicros>397833333</powerPriceMicros>
    </CtPeriod>
    <CtPeriod id="248">
      <id>104</id>
      <index>104</index>
      <powerPriceMicros>397833333</powerPriceMicros>
    </CtPeriod>
    <CtPeriod id="249">
      <id>105</id>
      <index>105</index>
      <powerPriceMicros>397833333</powerPriceMicros>
    </CtPeriod>
    <CtPeriod id="250">
      <id>106</id>
      <index>106</index>
      <powerPriceMicros>397833333</powerPriceMicros>
    </CtPeriod>
    <CtPeriod id="251">
      <id>107</id>
      <index>107</index>
      <powerPriceMicros>397833333</powerPriceMicros>
    </CtPeriod>
    <CtPeriod id="252">
      <id>108</id>
      <index>108</index>
      <powerPriceMicros>289833333</powerPriceMicros>
    </CtPeriod>
    <CtPeriod id="253">
      <id>109</id>
      <index>109</index>
      <powerPriceMicros>289833333</powerPriceMicros>
    </CtPeriod>
    <CtPeriod id="254">
      <id>110</id>
      <index>110</index>
      <powerPriceMicros>289833333</powerPriceMicros>
    </CtPeriod>
    <CtPeriod id="255">
      <id>111</id>
      <index>111</index>
      <powerPriceMicros>289833333</powerPriceMicros>
    </CtPeriod>
    <CtPeriod id="256">
      <id>112</id>
      <index>112</index>
      <powerPriceMicros>289833333</powerPriceMicros>
    </CtPeriod>
    <CtPeriod id="257">
      <id>113</id>
      <index>113</index>
      <powerPriceMicros>289833333</powerPriceMicros>
    </CtPeriod>
    <CtPeriod id="258">
      <id>114</id>
      <index>114</index>
      <powerPriceMicros>398000000</powerPriceMicros>
    </CtPeriod>
    <CtPeriod id="259">
      <id>115</id>
      <index>115</index>
      <powerPriceMicros>398000000</powerPriceMicros>
    </CtPeriod>
    <CtPeriod id="260">
      <id>116</id>
      <index>116</index>
      <powerPriceMicros>398000000</powerPriceMicros>
    </CtPeriod>
    <CtPeriod id="261">
      <id>117</id>
      <index>117</index>
      <powerPriceMicros>398000000</powerPriceMicros>
    </CtPeriod>
    <CtPeriod id="262">
      <id>118</id>
      <index>118</index>
      <powerPriceMicros>398000000</powerPriceMicros>
    </CtPeriod>
    <CtPeriod id="263">
      <id>119</id>
      <index>119</index>
      <powerPriceMicros>398000000</powerPriceMicros>
    </CtPeriod>
    <CtPeriod id="264">
      <id>120</id>
      <index>120</index>
      <powerPriceMicros>338666667</powerPriceMicros>
    </CtPeriod>
    <CtPeriod id="265">
      <id>121</id>
      <index>121</index>
      <powerPriceMicros>338666667</powerPriceMicros>
    </CtPeriod>
    <CtPeriod id="266">
      <id>122</id>
      <index>122</index>
      <powerPriceMicros>338666667</powerPriceMicros>
    </CtPeriod>
    <CtPeriod id="267">
      <id>123</id>
      <index>123</index>
      <powerPriceMicros>338666667</powerPriceMicros>
    </CtPeriod>
    <CtPeriod id="268">
      <id>124</id>
      <index>124</index>
      <powerPriceMicros>338666667</powerPriceMicros>
    </CtPeriod>
    <CtPeriod id="269">
      <id>125</id>
      <index>125</index>
      <powerPriceMicros>338666667</powerPriceMicros>
    </CtPeriod>
    <CtPeriod id="270">
      <id>126</id>
      <index>126</index>
      <powerPriceMicros>338666667</powerPriceMicros>
    </CtPeriod>
    <CtPeriod id="271">
      <id>127</id>
      <index>127</index>
      <powerPriceMicros>338666667</powerPriceMicros>
    </CtPeriod>
    <CtPeriod id="272">
      <id>128</id>
      <index>128</index>
      <powerPriceMicros>338666667</powerPriceMicros>
    </CtPeriod>
    <CtPeriod id="273">
      <id>129</id>
      <index>129</index>
      <powerPriceMicros>338666667</powerPriceMicros>
    </CtPeriod>
    <CtPeriod id="274">
      <id>130</id>
      <index>130</index>
      <powerPriceMicros>338666667</powerPriceMicros>
    </CtPeriod>
    <CtPeriod id="275">
      <id>131</id>
      <index>131</index>
      <powerPriceMicros>338666667</powerPriceMicros>
    </CtPeriod>
    <CtPeriod id="276">
      <id>132</id>
      <index>132</index>
      <powerPriceMicros>397833333</powerPriceMicros>
    </CtPeriod>
    <CtPeriod id="277">
      <id>133</id>
      <index>133</index>
      <powerPriceMicros>397833333</powerPriceMicros>
    </CtPeriod>
    <CtPeriod id="278">
      <id>134</id>
      <index>134</index>
      <powerPriceMicros>397833333</powerPriceMicros>
    </CtPeriod>
    <CtPeriod id="279">
      <id>135</id>
      <index>135</index>
      <powerPriceMicros>397833333</powerPriceMicros>
    </CtPeriod>
    <CtPeriod id="280">
      <id>136</id>
      <index>136</index>
      <powerPriceMicros>397833333</powerPriceMicros>
    </CtPeriod>
    <CtPeriod id="281">
      <id>137</id>
      <index>137</index>
      <powerPriceMicros>397833333</powerPriceMicros>
    </CtPeriod>
    <CtPeriod id="282">
      <id>138</id>
      <index>138</index>
      <powerPriceMicros>398000000</powerPriceMicros>
    </CtPeriod>
    <CtPeriod id="283">
      <id>139</id>
      <index>139</index>
      <powerPriceMicros>398000000</powerPriceMicros>
    </CtPeriod>
    <CtPeriod id="284">
      <id>140</id>
      <index>140</index>
      <powerPriceMicros>398000000</powerPriceMicros>
    </CtPeriod>
    <CtPeriod id="285">
      <id>141</id>
      <index>141</index>
      <powerPriceMicros>398000000</powerPriceMicros>
    </CtPeriod>
    <CtPeriod id="286">
      <id>142</id>
      <index>142</index>
      <powerPriceMicros>398000000</powerPriceMicros>
    </CtPeriod>
    <CtPeriod id="287">
      <id>143</id>
      <index>143</index>
      <powerPriceMicros>398000000</powerPriceMicros>
    </CtPeriod>
    <CtPeriod id="288">
      <id>144</id>
      <index>144</index>
      <powerPriceMicros>398000000</powerPriceMicros>
    </CtPeriod>
    <CtPeriod id="289">
      <id>145</id>
      <index>145</index>
      <powerPriceMicros>398000000</powerPriceMicros>
    </CtPeriod>
    <CtPeriod id="290">
      <id>146</id>
      <index>146</index>
      <powerPriceMicros>398000000</powerPriceMicros>
    </CtPeriod>
    <CtPeriod id="291">
      <id>147</id>
      <index>147</index>
      <powerPriceMicros>398000000</powerPriceMicros>
    </CtPeriod>
    <CtPeriod id="292">
      <id>148</id>
      <index>148</index>
      <powerPriceMicros>398000000</powerPriceMicros>
    </CtPeriod>
    <CtPeriod id="293">
      <id>149</id>
      <index>149</index>
      <powerPriceMicros>398000000</powerPriceMicros>
    </CtPeriod>
    <CtPeriod id="294">
      <id>150</id>
      <index>150</index>
      <powerPriceMicros>398000000</powerPriceMicros>
    </CtPeriod>
    <CtPeriod id="295">
      <id>151</id>
      <index>151</index>
      <powerPriceMicros>398000000</powerPriceMicros>
    </CtPeriod>
    <CtPeriod id="296">
      <id>152</id>
      <index>152</index>
      <powerPriceMicros>398000000</powerPriceMicros>
    </CtPeriod>
    <CtPeriod id="297">
      <id>153</id>
      <index>153</index>
      <powerPriceMicros>398000000</powerPriceMicros>
    </CtPeriod>
    <CtPeriod id="298">
      <id>154</id>
      <index>154</index>
      <powerPriceMicros>398000000</powerPriceMicros>
    </CtPeriod>
    <CtPeriod id="299">
      <id>155</id>
      <index>155</index>
      <powerPriceMicros>398000000</powerPriceMicros>
    </CtPeriod>
    <CtPeriod id="300">
      <id>156</id>
      <index>156</index>
      <powerPriceMicros>398000000</powerPriceMicros>
    </CtPeriod>
    <CtPeriod id="301">
      <id>157</id>
      <index>157</index>
      <powerPriceMicros>398000000</powerPriceMicros>
    </CtPeriod>
    <CtPeriod id="302">
      <id>158</id>
      <index>158</index>
      <powerPriceMicros>398000000</powerPriceMicros>
    </CtPeriod>
    <CtPeriod id="303">
      <id>159</id>
      <index>159</index>
      <powerPriceMicros>398000000</powerPriceMicros>
    </CtPeriod>
    <CtPeriod id="304">
      <id>160</id>
      <index>160</index>
      <powerPriceMicros>398000000</powerPriceMicros>
    </CtPeriod>
    <CtPeriod id="305">
      <id>161</id>
      <index>161</index>
      <powerPriceMicros>398000000</powerPriceMicros>
    </CtPeriod>
    <CtPeriod id="306">
      <id>162</id>
      <index>162</index>
      <powerPriceMicros>398000000</powerPriceMicros>
    </CtPeriod>
    <CtPeriod id="307">
      <id>163</id>
      <index>163</index>
      <powerPriceMicros>398000000</powerPriceMicros>
    </CtPeriod>
    <CtPeriod id="308">
      <id>164</id>
      <index>164</index>
      <powerPriceMicros>398000000</powerPriceMicros>
    </CtPeriod>
    <CtPeriod id="309">
      <id>165</id>
      <index>165</index>
      <powerPriceMicros>398000000</powerPriceMicros>
    </CtPeriod>
    <CtPeriod id="310">
      <id>166</id>
      <index>166</index>
      <powerPriceMicros>398000000</powerPriceMicros>
    </CtPeriod>
    <CtPeriod id="311">
      <id>167</id>
      <index>167</index>
      <powerPriceMicros>398000000</powerPriceMicros>
    </CtPeriod>
    <CtPeriod id="312">
      <id>168</id>
      <index>168</index>
      <powerPriceMicros>398000000</powerPriceMicros>
    </CtPeriod>
    <CtPeriod id="313">
      <id>169</id>
      <index>169</index>
      <powerPriceMicros>398000000</powerPriceMicros>
    </CtPeriod>
    <CtPeriod id="314">
      <id>170</id>
      <index>170</index>
      <powerPriceMicros>398000000</powerPriceMicros>
    </CtPeriod>
    <CtPeriod id="315">
      <id>171</id>
      <index>171</index>
      <powerPriceMicros>398000000</powerPriceMicros>
    </CtPeriod>
    <CtPeriod id="316">
      <id>172</id>
      <index>172</index>
      <powerPriceMicros>398000000</powerPriceMicros>
    </CtPeriod>
    <CtPeriod id="317">
      <id>173</id>
      <index>173</index>
      <powerPriceMicros>398000000</powerPriceMicros>
    </CtPeriod>
    <CtPeriod id="318">
      <id>174</id>
      <index>174</index>
      <powerPriceMicros>398000000</powerPriceMicros>
    </CtPeriod>
    <CtPeriod id="319">
      <id>175</id>
      <index>175</index>
      <powerPriceMicros>398000000</powerPriceMicros>
    </CtPeriod>
    <CtPeriod id="320">
      <id>176</id>
      <index>176</index>
      <powerPriceMicros>398000000</powerPriceMicros>
    </CtPeriod>
    <CtPeriod id="321">
      <id>177</id>
      <index>177</index>
      <powerPriceMicros>398000000</powerPriceMicros>
    </CtPeriod>
    <CtPeriod id="322">
      <id>178</id>
      <index>178</index>
      <powerPriceMicros>398000000</powerPriceMicros>
    </CtPeriod>
    <CtPeriod id="323">
      <id>179</id>
      <index>179</index>
      <powerPriceMicros>398000000</powerPriceMicros>
    </CtPeriod>
    <CtPeriod id="324">
      <id>180</id>
      <index>180</index>
      <powerPriceMicros>398000000</powerPriceMicros>
    </CtPeriod>
    <CtPeriod id="325">
      <id>181</id>
      <index>181</index>
      <powerPriceMicros>398000000</powerPriceMicros>
    </CtPeriod>
    <CtPeriod id="326">
      <id>182</id>
      <index>182</index>
      <powerPriceMicros>398000000</powerPriceMicros>
    </CtPeriod>
    <CtPeriod id="327">
      <id>183</id>
      <index>183</index>
      <powerPriceMicros>398000000</powerPriceMicros>
    </CtPeriod>
    <CtPeriod id="328">
      <id>184</id>
      <index>184</index>
      <powerPriceMicros>398000000</powerPriceMicros>
    </CtPeriod>
    <CtPeriod id="329">
      <id>185</id>
      <index>185</index>
      <powerPriceMicros>398000000</powerPriceMicros>
    </CtPeriod>
    <CtPeriod id="330">
      <id>186</id>
      <index>186</index>
      <powerPriceMicros>405833333</powerPriceMicros>
    </CtPeriod>
    <CtPeriod id="331">
      <id>187</id>
      <index>187</index>
      <powerPriceMicros>405833333</powerPriceMicros>
    </CtPeriod>
    <CtPeriod id="332">
      <id>188</id>
      <index>188</index>
      <powerPriceMicros>405833333</powerPriceMicros>
    </CtPeriod>
    <CtPeriod id="333">
      <id>189</id>
      <index>189</index>
      <powerPriceMicros>405833333</powerPriceMicros>
    </CtPeriod>
    <CtPeriod id="334">
      <id>190</id>
      <index>190</index>
      <powerPriceMicros>405833333</powerPriceMicros>
    </CtPeriod>
    <CtPeriod id="335">
      <id>191</id>
      <index>191</index>
      <powerPriceMicros>405833333</powerPriceMicros>
    </CtPeriod>
    <CtPeriod id="336">
      <id>192</id>
      <index>192</index>
      <powerPriceMicros>405833333</powerPriceMicros>
    </CtPeriod>
    <CtPeriod id="337">
      <id>193</id>
      <index>193</index>
      <powerPriceMicros>405833333</powerPriceMicros>
    </CtPeriod>
    <CtPeriod id="338">
      <id>194</id>
      <index>194</index>
      <powerPriceMicros>405833333</powerPriceMicros>
    </CtPeriod>
    <CtPeriod id="339">
      <id>195</id>
      <index>195</index>
      <powerPriceMicros>405833333</powerPriceMicros>
    </CtPeriod>
    <CtPeriod id="340">
      <id>196</id>
      <index>196</index>
      <powerPriceMicros>405833333</powerPriceMicros>
    </CtPeriod>
    <CtPeriod id="341">
      <id>197</id>
      <index>197</index>
      <powerPriceMicros>405833333</powerPriceMicros>
    </CtPeriod>
    <CtPeriod id="342">
      <id>198</id>
      <index>198</index>
      <powerPriceMicros>405833333</powerPriceMicros>
    </CtPeriod>
    <CtPeriod id="343">
      <id>199</id>
      <index>199</index>
      <powerPriceMicros>405833333</powerPriceMicros>
    </CtPeriod>
    <CtPeriod id="344">
      <id>200</id>
      <index>200</index>
      <powerPriceMicros>405833333</powerPriceMicros>
    </CtPeriod>
    <CtPeriod id="345">
      <id>201</id>
      <index>201</index>
      <powerPriceMicros>405833333</powerPriceMicros>
    </CtPeriod>
    <CtPeriod id="346">
      <id>202</id>
      <index>202</index>
      <powerPriceMicros>405833333</powerPriceMicros>
    </CtPeriod>
    <CtPeriod id="347">
      <id>203</id>
      <index>203</index>
      <powerPriceMicros>405833333</powerPriceMicros>
    </CtPeriod>
    <CtPeriod id="348">
      <id>204</id>
      <index>204</index>
      <powerPriceMicros>409250000</powerPriceMicros>
    </CtPeriod>
    <CtPeriod id="349">
      <id>205</id>
      <index>205</index>
      <powerPriceMicros>409250000</powerPriceMicros>
    </CtPeriod>
    <CtPeriod id="350">
      <id>206</id>
      <index>206</index>
      <powerPriceMicros>409250000</powerPriceMicros>
    </CtPeriod>
    <CtPeriod id="351">
      <id>207</id>
      <index>207</index>
      <powerPriceMicros>409250000</powerPriceMicros>
    </CtPeriod>
    <CtPeriod id="352">
      <id>208</id>
      <index>208</index>
      <powerPriceMicros>409250000</powerPriceMicros>
    </CtPeriod>
    <CtPeriod id="353">
      <id>209</id>
      <index>209</index>
      <powerPriceMicros>409250000</powerPriceMicros>
    </CtPeriod>
    <CtPeriod id="354">
      <id>210</id>
      <index>210</index>
      <powerPriceMicros>2286083333</powerPriceMicros>
    </CtPeriod>
    <CtPeriod id="355">
      <id>211</id>
      <index>211</index>
      <powerPriceMicros>2286083333</powerPriceMicros>
    </CtPeriod>
    <CtPeriod id="356">
      <id>212</id>
      <index>212</index>
      <powerPriceMicros>2286083333</powerPriceMicros>
    </CtPeriod>
    <CtPeriod id="357">
      <id>213</id>
      <index>213</index>
      <powerPriceMicros>2286083333</powerPriceMicros>
    </CtPeriod>
    <CtPeriod id="358">
      <id>214</id>
      <index>214</index>
      <powerPriceMicros>2286083333</powerPriceMicros>
    </CtPeriod>
    <CtPeriod id="359">
      <id>215</id>
      <index>215</index>
      <powerPriceMicros>2286083333</powerPriceMicros>
    </CtPeriod>
    <CtPeriod id="360">
      <id>216</id>
      <index>216</index>
      <powerPriceMicros>2286083333</powerPriceMicros>
    </CtPeriod>
    <CtPeriod id="361">
      <id>217</id>
      <index>217</index>
      <powerPriceMicros>2286083333</powerPriceMicros>
    </CtPeriod>
    <CtPeriod id="362">
      <id>218</id>
      <index>218</index>
      <powerPriceMicros>2286083333</powerPriceMicros>
    </CtPeriod>
    <CtPeriod id="363">
      <id>219</id>
      <index>219</index>
      <powerPriceMicros>2286083333</powerPriceMicros>
    </CtPeriod>
    <CtPeriod id="364">
      <id>220</id>
      <index>220</index>
      <powerPriceMicros>2286083333</powerPriceMicros>
    </CtPeriod>
    <CtPeriod id="365">
      <id>221</id>
      <index>221</index>
      <powerPriceMicros>2286083333</powerPriceMicros>
    </CtPeriod>
    <CtPeriod id="366">
      <id>222</id>
      <index>222</index>
      <powerPriceMicros>417333333</powerPriceMicros>
    </CtPeriod>
    <CtPeriod id="367">
      <id>223</id>
      <index>223</index>
      <powerPriceMicros>417333333</powerPriceMicros>
    </CtPeriod>
    <CtPeriod id="368">
      <id>224</id>
      <index>224</index>
      <powerPriceMicros>417333333</powerPriceMicros>
    </CtPeriod>
    <CtPeriod id="369">
      <id>225</id>
      <index>225</index>
      <powerPriceMicros>417333333</powerPriceMicros>
    </CtPeriod>
    <CtPeriod id="370">
      <id>226</id>
      <index>226</index>
      <powerPriceMicros>417333333</powerPriceMicros>
    </CtPeriod>
    <CtPeriod id="371">
      <id>227</id>
      <index>227</index>
      <powerPriceMicros>417333333</powerPriceMicros>
    </CtPeriod>
    <CtPeriod id="372">
      <id>228</id>
      <index>228</index>
      <powerPriceMicros>409250000</powerPriceMicros>
    </CtPeriod>
    <CtPeriod id="373">
      <id>229</id>
      <index>229</index>
      <powerPriceMicros>409250000</powerPriceMicros>
    </CtPeriod>
    <CtPeriod id="374">
      <id>230</id>
      <index>230</index>
      <powerPriceMicros>409250000</powerPriceMicros>
    </CtPeriod>
    <CtPeriod id="375">
      <id>231</id>
      <index>231</index>
      <powerPriceMicros>409250000</powerPriceMicros>
    </CtPeriod>
    <CtPeriod id="376">
      <id>232</id>
      <index>232</index>
      <powerPriceMicros>409250000</powerPriceMicros>
    </CtPeriod>
    <CtPeriod id="377">
      <id>233</id>
      <index>233</index>
      <powerPriceMicros>409250000</powerPriceMicros>
    </CtPeriod>
    <CtPeriod id="378">
      <id>234</id>
      <index>234</index>
      <powerPriceMicros>405833333</powerPriceMicros>
    </CtPeriod>
    <CtPeriod id="379">
      <id>235</id>
      <index>235</index>
      <powerPriceMicros>405833333</powerPriceMicros>
    </CtPeriod>
    <CtPeriod id="380">
      <id>236</id>
      <index>236</index>
      <powerPriceMicros>405833333</powerPriceMicros>
    </CtPeriod>
    <CtPeriod id="381">
      <id>237</id>
      <index>237</index>
      <powerPriceMicros>405833333</powerPriceMicros>
    </CtPeriod>
    <CtPeriod id="382">
      <id>238</id>
      <index>238</index>
      <powerPriceMicros>405833333</powerPriceMicros>
    </CtPeriod>
    <CtPeriod id="383">
      <id>239</id>
      <index>239</index>
      <powerPriceMicros>405833333</powerPriceMicros>
    </CtPeriod>
    <CtPeriod id="384">
      <id>240</id>
      <index>240</index>
      <powerPriceMicros>405833333</powerPriceMicros>
    </CtPeriod>
    <CtPeriod id="385">
      <id>241</id>
      <index>241</index>
      <powerPriceMicros>405833333</powerPriceMicros>
    </CtPeriod>
    <CtPeriod id="386">
      <id>242</id>
      <index>242</index>
      <powerPriceMicros>405833333</powerPriceMicros>
    </CtPeriod>
    <CtPeriod id="387">
      <id>243</id>
      <index>243</index>
      <powerPriceMicros>405833333</powerPriceMicros>
    </CtPeriod>
    <CtPeriod id="388">
      <id>244</id>
      <index>244</index>
      <powerPriceMicros>405833333</powerPriceMicros>
    </CtPeriod>
    <CtPeriod id="389">
      <id>245</id>
      <index>245</index>
      <powerPriceMicros>405833333</powerPriceMicros>
    </CtPeriod>
    <CtPeriod id="390">
      <id>246</id>
      <index>246</index>
      <powerPriceMicros>405833333</powerPriceMicros>
    </CtPeriod>
    <CtPeriod id="391">
      <id>247</id>
      <index>247</index>
      <powerPriceMicros>405833333</powerPriceMicros>
    </CtPeriod>
    <CtPeriod id="392">
      <id>248</id>
      <index>248</index>
      <powerPriceMicros>405833333</powerPriceMicros>
    </CtPeriod>
    <CtPeriod id="393">
      <id>249</id>
      <index>249</index>
      <powerPriceMicros>405833333</powerPriceMicros>
    </CtPeriod>
    <CtPeriod id="394">
      <id>250</id>
      <index>250</index>
      <powerPriceMicros>405833333</powerPriceMicros>
    </CtPeriod>
    <CtPeriod id="395">
      <id>251</id>
      <index>251</index>
      <powerPriceMicros>405833333</powerPriceMicros>
    </CtPeriod>
    <CtPeriod id="396">
      <id>252</id>
      <index>252</index>
      <powerPriceMicros>405833333</powerPriceMicros>
    </CtPeriod>
    <CtPeriod id="397">
      <id>253</id>
      <index>253</index>
      <powerPriceMicros>405833333</powerPriceMicros>
    </CtPeriod>
    <CtPeriod id="398">
      <id>254</id>
      <index>254</index>
      <powerPriceMicros>405833333</powerPriceMicros>
    </CtPeriod>
    <CtPeriod id="399">
      <id>255</id>
      <index>255</index>
      <powerPriceMicros>405833333</powerPriceMicros>
    </CtPeriod>
    <CtPeriod id="400">
      <id>256</id>
      <index>256</index>
      <powerPriceMicros>405833333</powerPriceMicros>
    </CtPeriod>
    <CtPeriod id="401">
      <id>257</id>
      <index>257</index>
      <powerPriceMicros>405833333</powerPriceMicros>
    </CtPeriod>
    <CtPeriod id="402">
      <id>258</id>
      <index>258</index>
      <powerPriceMicros>405833333</powerPriceMicros>
    </CtPeriod>
    <CtPeriod id="403">
      <id>259</id>
      <index>259</index>
      <powerPriceMicros>405833333</powerPriceMicros>
    </CtPeriod>
    <CtPeriod id="404">
      <id>260</id>
      <index>260</index>
      <powerPriceMicros>405833333</powerPriceMicros>
    </CtPeriod>
    <CtPeriod id="405">
      <id>261</id>
      <index>261</index>
      <powerPriceMicros>405833333</powerPriceMicros>
    </CtPeriod>
    <CtPeriod id="406">
      <id>262</id>
      <index>262</index>
      <powerPriceMicros>405833333</powerPriceMicros>
    </CtPeriod>
    <CtPeriod id="407">
      <id>263</id>
      <index>263</index>
      <powerPriceMicros>405833333</powerPriceMicros>
    </CtPeriod>
    <CtPeriod id="408">
      <id>264</id>
      <index>264</index>
      <powerPriceMicros>401500000</powerPriceMicros>
    </CtPeriod>
    <CtPeriod id="409">
      <id>265</id>
      <index>265</index>
      <powerPriceMicros>401500000</powerPriceMicros>
    </CtPeriod>
    <CtPeriod id="410">
      <id>266</id>
      <index>266</index>
      <powerPriceMicros>401500000</powerPriceMicros>
    </CtPeriod>
    <CtPeriod id="411">
      <id>267</id>
      <index>267</index>
      <powerPriceMicros>401500000</powerPriceMicros>
    </CtPeriod>
    <CtPeriod id="412">
      <id>268</id>
      <index>268</index>
      <powerPriceMicros>401500000</powerPriceMicros>
    </CtPeriod>
    <CtPeriod id="413">
      <id>269</id>
      <index>269</index>
      <powerPriceMicros>401500000</powerPriceMicros>
    </CtPeriod>
    <CtPeriod id="414">
      <id>270</id>
      <index>270</index>
      <powerPriceMicros>398000000</powerPriceMicros>
    </CtPeriod>
    <CtPeriod id="415">
      <id>271</id>
      <index>271</index>
      <powerPriceMicros>398000000</powerPriceMicros>
    </CtPeriod>
    <CtPeriod id="416">
      <id>272</id>
      <index>272</index>
      <powerPriceMicros>398000000</powerPriceMicros>
    </CtPeriod>
    <CtPeriod id="417">
      <id>273</id>
      <index>273</index>
      <powerPriceMicros>398000000</powerPriceMicros>
    </CtPeriod>
    <CtPeriod id="418">
      <id>274</id>
      <index>274</index>
      <powerPriceMicros>398000000</powerPriceMicros>
    </CtPeriod>
    <CtPeriod id="419">
      <id>275</id>
      <index>275</index>
      <powerPriceMicros>398000000</powerPriceMicros>
    </CtPeriod>
    <CtPeriod id="420">
      <id>276</id>
      <index>276</index>
      <powerPriceMicros>405833333</powerPriceMicros>
    </CtPeriod>
    <CtPeriod id="421">
      <id>277</id>
      <index>277</index>
      <powerPriceMicros>405833333</powerPriceMicros>
    </CtPeriod>
    <CtPeriod id="422">
      <id>278</id>
      <index>278</index>
      <powerPriceMicros>405833333</powerPriceMicros>
    </CtPeriod>
    <CtPeriod id="423">
      <id>279</id>
      <index>279</index>
      <powerPriceMicros>405833333</powerPriceMicros>
    </CtPeriod>
    <CtPeriod id="424">
      <id>280</id>
      <index>280</index>
      <powerPriceMicros>405833333</powerPriceMicros>
    </CtPeriod>
    <CtPeriod id="425">
      <id>281</id>
      <index>281</index>
      <powerPriceMicros>405833333</powerPriceMicros>
    </CtPeriod>
    <CtPeriod id="426">
      <id>282</id>
      <index>282</index>
      <powerPriceMicros>405833333</powerPriceMicros>
    </CtPeriod>
    <CtPeriod id="427">
      <id>283</id>
      <index>283</index>
      <powerPriceMicros>405833333</powerPriceMicros>
    </CtPeriod>
    <CtPeriod id="428">
      <id>284</id>
      <index>284</index>
      <powerPriceMicros>405833333</powerPriceMicros>
    </CtPeriod>
    <CtPeriod id="429">
      <id>285</id>
      <index>285</index>
      <powerPriceMicros>405833333</powerPriceMicros>
    </CtPeriod>
    <CtPeriod id="430">
      <id>286</id>
      <index>286</index>
      <powerPriceMicros>405833333</powerPriceMicros>
    </CtPeriod>
    <CtPeriod id="431">
      <id>287</id>
      <index>287</index>
      <powerPriceMicros>405833333</powerPriceMicros>
    </CtPeriod>
  </periodList>
  <taskAssignmentList id="432">
    <CtTaskAssignment id="433">
      <id>0</id>
      <task reference="18"/>
    </CtTaskAssignment>
    <CtTaskAssignment id="434">
      <id>1</id>
      <task reference="23"/>
    </CtTaskAssignment>
    <CtTaskAssignment id="435">
      <id>2</id>
      <task reference="28"/>
    </CtTaskAssignment>
    <CtTaskAssignment id="436">
      <id>3</id>
      <task reference="33"/>
    </CtTaskAssignment>
    <CtTaskAssignment id="437">
      <id>4</id>
      <task reference="38"/>
    </CtTaskAssignment>
    <CtTaskAssignment id="438">
      <id>5</id>
      <task reference="43"/>
    </CtTaskAssignment>
    <CtTaskAssignment id="439">
      <id>6</id>
      <task reference="48"/>
    </CtTaskAssignment>
    <CtTaskAssignment id="440">
      <id>7</id>
      <task reference="53"/>
    </CtTaskAssignment>
    <CtTaskAssignment id="441">
      <id>8</id>
      <task reference="58"/>
    </CtTaskAssignment>
    <CtTaskAssignment id="442">
      <id>9</id>
      <task reference="63"/>
    </CtTaskAssignment>
    <CtTaskAssignment id="443">
      <id>10</id>
      <task reference="68"/>
    </CtTaskAssignment>
    <CtTaskAssignment id="444">
      <id>11</id>
      <task reference="73"/>
    </CtTaskAssignment>
    <CtTaskAssignment id="445">
      <id>12</id>
      <task reference="78"/>
    </CtTaskAssignment>
    <CtTaskAssignment id="446">
      <id>13</id>
      <task reference="83"/>
    </CtTaskAssignment>
    <CtTaskAssignment id="447">
      <id>14</id>
      <task reference="88"/>
    </CtTaskAssignment>
    <CtTaskAssignment id="448">
      <id>15</id>
      <task reference="93"/>
    </CtTaskAssignment>
    <CtTaskAssignment id="449">
      <id>16</id>
      <task reference="98"/>
    </CtTaskAssignment>
    <CtTaskAssignment id="450">
      <id>17</id>
      <task reference="103"/>
    </CtTaskAssignment>
    <CtTaskAssignment id="451">
      <id>18</id>
      <task reference="108"/>
    </CtTaskAssignment>
    <CtTaskAssignment id="452">
      <id>19</id>
      <task reference="113"/>
    </CtTaskAssignment>
    <CtTaskAssignment id="453">
      <id>20</id>
      <task reference="118"/>
    </CtTaskAssignment>
    <CtTaskAssignment id="454">
      <id>21</id>
      <task reference="123"/>
    </CtTaskAssignment>
    <CtTaskAssignment id="455">
      <id>22</id>
      <task reference="128"/>
    </CtTaskAssignment>
    <CtTaskAssignment id="456">
      <id>23</id>
      <task reference="133"/>
    </CtTaskAssignment>
    <CtTaskAssignment id="457">
      <id>24</id>
      <task reference="138"/>
    </CtTaskAssignment>
  </taskAssignmentList>
</CtCheapTimeSolution>