<CloudBalance id="1">
  <id>0</id>
  <computerList id="2">
    <CloudComputer id="3">
      <id>0</id>
      <cpuPower>24</cpuPower>
      <memory>96</memory>
      <networkBandwidth>16</networkBandwidth>
      <cost>4800</cost>
    </CloudComputer>
    <CloudComputer id="4">
      <id>1</id>
      <cpuPower>6</cpuPower>
      <memory>4</memory>
      <networkBandwidth>6</networkBandwidth>
      <cost>660</cost>
    </CloudComputer>
    <CloudComputer id="5">
      <id>2</id>
      <cpuPower>6</cpuPower>
      <memory>16</memory>
      <networkBandwidth>4</networkBandwidth>
      <cost>680</cost>
    </CloudComputer>
    <CloudComputer id="6">
      <id>3</id>
      <cpuPower>8</cpuPower>
      <memory>32</memory>
      <networkBandwidth>12</networkBandwidth>
      <cost>1270</cost>
    </CloudComputer>
    <CloudComputer id="7">
      <id>4</id>
      <cpuPower>3</cpuPower>
      <memory>2</memory>
      <networkBandwidth>2</networkBandwidth>
      <cost>350</cost>
    </CloudComputer>
    <CloudComputer id="8">
      <id>5</id>
      <cpuPower>8</cpuPower>
      <memory>32</memory>
      <networkBandwidth>4</networkBandwidth>
      <cost>870</cost>
    </CloudComputer>
    <CloudComputer id="9">
      <id>6</id>
      <cpuPower>3</cpuPower>
      <memory>2</memory>
      <networkBandwidth>2</networkBandwidth>
      <cost>350</cost>
    </CloudComputer>
    <CloudComputer id="10">
      <id>7</id>
      <cpuPower>3</cpuPower>
      <memory>2</memory>
      <networkBandwidth>2</networkBandwidth>
      <cost>350</cost>
    </CloudComputer>
    <CloudComputer id="11">
      <id>8</id>
      <cpuPower>12</cpuPower>
      <memory>32</memory>
      <networkBandwidth>16</networkBandwidth>
      <cost>1600</cost>
    </CloudComputer>
    <CloudComputer id="12">
      <id>9</id>
      <cpuPower>3</cpuPower>
      <memory>2</memory>
      <networkBandwidth>2</networkBandwidth>
      <cost>350</cost>
    </CloudComputer>
    <CloudComputer id="13">
      <id>10</id>
      <cpuPower>12</cpuPower>
      <memory>32</memory>
      <networkBandwidth>16</networkBandwidth>
      <cost>1600</cost>
    </CloudComputer>
    <CloudComputer id="14">
      <id>11</id>
      <cpuPower>24</cpuPower>
      <memory>64</memory>
      <networkBandwidth>20</networkBandwidth>
      <cost>4600</cost>
    </CloudComputer>
    <CloudComputer id="15">
      <id>12</id>
      <cpuPower>4</cpuPower>
      <memory>4</memory>
      <networkBandwidth>6</networkBandwidth>
      <cost>620</cost>
    </CloudComputer>
    <CloudComputer id="16">
      <id>13</id>
      <cpuPower>3</cpuPower>
      <memory>4</memory>
      <networkBandwidth>2</networkBandwidth>
      <cost>390</cost>
    </CloudComputer>
    <CloudComputer id="17">
      <id>14</id>
      <cpuPower>12</cpuPower>
      <memory>32</memory>
      <networkBandwidth>12</networkBandwidth>
      <cost>1400</cost>
    </CloudComputer>
    <CloudComputer id="18">
      <id>15</id>
      <cpuPower>3</cpuPower>
      <memory>2</memory>
      <networkBandwidth>2</networkBandwidth>
      <cost>350</cost>
    </CloudComputer>
    <CloudComputer id="19">
      <id>16</id>
      <cpuPower>8</cpuPower>
      <memory>16</memory>
      <networkBandwidth>12</networkBandwidth>
      <cost>1170</cost>
    </CloudComputer>
    <CloudComputer id="20">
      <id>17</id>
      <cpuPower>3</cpuPower>
      <memory>2</memory>
      <networkBandwidth>2</networkBandwidth>
      <cost>350</cost>
    </CloudComputer>
    <CloudComputer id="21">
      <id>18</id>
      <cpuPower>16</cpuPower>
      <memory>64</memory>
      <networkBandwidth>12</networkBandwidth>
      <cost>2200</cost>
    </CloudComputer>
    <CloudComputer id="22">
      <id>19</id>
      <cpuPower>16</cpuPower>
      <memory>96</memory>
      <networkBandwidth>20</networkBandwidth>
      <cost>3000</cost>
    </CloudComputer>
    <CloudComputer id="23">
      <id>20</id>
      <cpuPower>12</cpuPower>
      <memory>32</memory>
      <networkBandwidth>8</networkBandwidth>
      <cost>1200</cost>
    </CloudComputer>
    <CloudComputer id="24">
      <id>21</id>
      <cpuPower>8</cpuPower>
      <memory>16</memory>
      <networkBandwidth>6</networkBandwidth>
      <cost>870</cost>
    </CloudComputer>
    <CloudComputer id="25">
      <id>22</id>
      <cpuPower>4</cpuPower>
      <memory>4</memory>
      <networkBandwidth>6</networkBandwidth>
      <cost>620</cost>
    </CloudComputer>
    <CloudComputer id="26">
      <id>23</id>
      <cpuPower>4</cpuPower>
      <memory>4</memory>
      <networkBandwidth>8</networkBandwidth>
      <cost>720</cost>
    </CloudComputer>
    <CloudComputer id="27">
      <id>24</id>
      <cpuPower>3</cpuPower>
      <memory>4</memory>
      <networkBandwidth>2</networkBandwidth>
      <cost>390</cost>
    </CloudComputer>
    <CloudComputer id="28">
      <id>25</id>
      <cpuPower>16</cpuPower>
      <memory>64</memory>
      <networkBandwidth>16</networkBandwidth>
      <cost>2400</cost>
    </CloudComputer>
    <CloudComputer id="29">
      <id>26</id>
      <cpuPower>8</cpuPower>
      <memory>16</memory>
      <networkBandwidth>8</networkBandwidth>
      <cost>970</cost>
    </CloudComputer>
    <CloudComputer id="30">
      <id>27</id>
      <cpuPower>8</cpuPower>
      <memory>16</memory>
      <networkBandwidth>6</networkBandwidth>
      <cost>870</cost>
    </CloudComputer>
    <CloudComputer id="31">
      <id>28</id>
      <cpuPower>8</cpuPower>
      <memory>16</memory>
      <networkBandwidth>12</networkBandwidth>
      <cost>1170</cost>
    </CloudComputer>
    <CloudComputer id="32">
      <id>29</id>
      <cpuPower>3</cpuPower>
      <memory>2</memory>
      <networkBandwidth>2</networkBandwidth>
      <cost>350</cost>
    </CloudComputer>
    <CloudComputer id="33">
      <id>30</id>
      <cpuPower>6</cpuPower>
      <memory>8</memory>
      <networkBandwidth>4</networkBandwidth>
      <cost>600</cost>
    </CloudComputer>
    <CloudComputer id="34">
      <id>31</id>
      <cpuPower>16</cpuPower>
      <memory>96</memory>
      <networkBandwidth>16</networkBandwidth>
      <cost>2800</cost>
    </CloudComputer>
    <CloudComputer id="35">
      <id>32</id>
      <cpuPower>8</cpuPower>
      <memory>32</memory>
      <networkBandwidth>8</networkBandwidth>
      <cost>1070</cost>
    </CloudComputer>
    <CloudComputer id="36">
      <id>33</id>
      <cpuPower>3</cpuPower>
      <memory>2</memory>
      <networkBandwidth>2</networkBandwidth>
      <cost>350</cost>
    </CloudComputer>
    <CloudComputer id="37">
      <id>34</id>
      <cpuPower>3</cpuPower>
      <memory>2</memory>
      <networkBandwidth>2</networkBandwidth>
      <cost>350</cost>
    </CloudComputer>
    <CloudComputer id="38">
      <id>35</id>
      <cpuPower>12</cpuPower>
      <memory>32</memory>
      <networkBandwidth>8</networkBandwidth>
      <cost>1200</cost>
    </CloudComputer>
    <CloudComputer id="39">
      <id>36</id>
      <cpuPower>8</cpuPower>
      <memory>32</memory>
      <networkBandwidth>8</networkBandwidth>
      <cost>1070</cost>
    </CloudComputer>
    <CloudComputer id="40">
      <id>37</id>
      <cpuPower>6</cpuPower>
      <memory>4</memory>
      <networkBandwidth>4</networkBandwidth>
      <cost>560</cost>
    </CloudComputer>
    <CloudComputer id="41">
      <id>38</id>
      <cpuPower>24</cpuPower>
      <memory>96</memory>
      <networkBandwidth>20</networkBandwidth>
      <cost>5000</cost>
    </CloudComputer>
    <CloudComputer id="42">
      <id>39</id>
      <cpuPower>4</cpuPower>
      <memory>8</memory>
      <networkBandwidth>4</networkBandwidth>
      <cost>560</cost>
    </CloudComputer>
    <CloudComputer id="43">
      <id>40</id>
      <cpuPower>4</cpuPower>
      <memory>4</memory>
      <networkBandwidth>8</networkBandwidth>
      <cost>720</cost>
    </CloudComputer>
    <CloudComputer id="44">
      <id>41</id>
      <cpuPower>4</cpuPower>
      <memory>16</memory>
      <networkBandwidth>4</networkBandwidth>
      <cost>640</cost>
    </CloudComputer>
    <CloudComputer id="45">
      <id>42</id>
      <cpuPower>16</cpuPower>
      <memory>64</memory>
      <networkBandwidth>16</networkBandwidth>
      <cost>2400</cost>
    </CloudComputer>
    <CloudComputer id="46">
      <id>43</id>
      <cpuPower>12</cpuPower>
      <memory>16</memory>
      <networkBandwidth>16</networkBandwidth>
      <cost>1500</cost>
    </CloudComputer>
    <CloudComputer id="47">
      <id>44</id>
      <cpuPower>24</cpuPower>
      <memory>96</memory>
      <networkBandwidth>20</networkBandwidth>
      <cost>5000</cost>
    </CloudComputer>
    <CloudComputer id="48">
      <id>45</id>
      <cpuPower>8</cpuPower>
      <memory>4</memory>
      <networkBandwidth>8</networkBandwidth>
      <cost>850</cost>
    </CloudComputer>
    <CloudComputer id="49">
      <id>46</id>
      <cpuPower>3</cpuPower>
      <memory>2</memory>
      <networkBandwidth>2</networkBandwidth>
      <cost>350</cost>
    </CloudComputer>
    <CloudComputer id="50">
      <id>47</id>
      <cpuPower>12</cpuPower>
      <memory>32</memory>
      <networkBandwidth>6</networkBandwidth>
      <cost>1100</cost>
    </CloudComputer>
    <CloudComputer id="51">
      <id>48</id>
      <cpuPower>24</cpuPower>
      <memory>64</memory>
      <networkBandwidth>16</networkBandwidth>
      <cost>4400</cost>
    </CloudComputer>
    <CloudComputer id="52">
      <id>49</id>
      <cpuPower>16</cpuPower>
      <memory>96</memory>
      <networkBandwidth>20</networkBandwidth>
      <cost>3000</cost>
    </CloudComputer>
    <CloudComputer id="53">
      <id>50</id>
      <cpuPower>12</cpuPower>
      <memory>32</memory>
      <networkBandwidth>8</networkBandwidth>
      <cost>1200</cost>
    </CloudComputer>
    <CloudComputer id="54">
      <id>51</id>
      <cpuPower>8</cpuPower>
      <memory>32</memory>
      <networkBandwidth>8</networkBandwidth>
      <cost>1070</cost>
    </CloudComputer>
    <CloudComputer id="55">
      <id>52</id>
      <cpuPower>6</cpuPower>
      <memory>2</memory>
      <networkBandwidth>6</networkBandwidth>
      <cost>620</cost>
    </CloudComputer>
    <CloudComputer id="56">
      <id>53</id>
      <cpuPower>12</cpuPower>
      <memory>64</memory>
      <networkBandwidth>16</networkBandwidth>
      <cost>1800</cost>
    </CloudComputer>
    <CloudComputer id="57">
      <id>54</id>
      <cpuPower>4</cpuPower>
      <memory>4</memory>
      <networkBandwidth>4</networkBandwidth>
      <cost>520</cost>
    </CloudComputer>
    <CloudComputer id="58">
      <id>55</id>
      <cpuPower>3</cpuPower>
      <memory>4</memory>
      <networkBandwidth>4</networkBandwidth>
      <cost>490</cost>
    </CloudComputer>
    <CloudComputer id="59">
      <id>56</id>
      <cpuPower>6</cpuPower>
      <memory>8</memory>
      <networkBandwidth>6</networkBandwidth>
      <cost>700</cost>
    </CloudComputer>
    <CloudComputer id="60">
      <id>57</id>
      <cpuPower>16</cpuPower>
      <memory>32</memory>
      <networkBandwidth>20</networkBandwidth>
      <cost>2400</cost>
    </CloudComputer>
    <CloudComputer id="61">
      <id>58</id>
      <cpuPower>4</cpuPower>
      <memory>4</memory>
      <networkBandwidth>4</networkBandwidth>
      <cost>520</cost>
    </CloudComputer>
    <CloudComputer id="62">
      <id>59</id>
      <cpuPower>16</cpuPower>
      <memory>64</memory>
      <networkBandwidth>16</networkBandwidth>
      <cost>2400</cost>
    </CloudComputer>
    <CloudComputer id="63">
      <id>60</id>
      <cpuPower>8</cpuPower>
      <memory>32</memory>
      <networkBandwidth>8</networkBandwidth>
      <cost>1070</cost>
    </CloudComputer>
    <CloudComputer id="64">
      <id>61</id>
      <cpuPower>24</cpuPower>
      <memory>96</memory>
      <networkBandwidth>20</networkBandwidth>
      <cost>5000</cost>
    </CloudComputer>
    <CloudComputer id="65">
      <id>62</id>
      <cpuPower>16</cpuPower>
      <memory>96</memory>
      <networkBandwidth>16</networkBandwidth>
      <cost>2800</cost>
    </CloudComputer>
    <CloudComputer id="66">
      <id>63</id>
      <cpuPower>24</cpuPower>
      <memory>96</memory>
      <networkBandwidth>20</networkBandwidth>
      <cost>5000</cost>
    </CloudComputer>
    <CloudComputer id="67">
      <id>64</id>
      <cpuPower>12</cpuPower>
      <memory>32</memory>
      <networkBandwidth>12</networkBandwidth>
      <cost>1400</cost>
    </CloudComputer>
    <CloudComputer id="68">
      <id>65</id>
      <cpuPower>12</cpuPower>
      <memory>32</memory>
      <networkBandwidth>12</networkBandwidth>
      <cost>1400</cost>
    </CloudComputer>
    <CloudComputer id="69">
      <id>66</id>
      <cpuPower>4</cpuPower>
      <memory>8</memory>
      <networkBandwidth>4</networkBandwidth>
      <cost>560</cost>
    </CloudComputer>
    <CloudComputer id="70">
      <id>67</id>
      <cpuPower>4</cpuPower>
      <memory>4</memory>
      <networkBandwidth>2</networkBandwidth>
      <cost>420</cost>
    </CloudComputer>
    <CloudComputer id="71">
      <id>68</id>
      <cpuPower>8</cpuPower>
      <memory>8</memory>
      <networkBandwidth>8</networkBandwidth>
      <cost>890</cost>
    </CloudComputer>
    <CloudComputer id="72">
      <id>69</id>
      <cpuPower>6</cpuPower>
      <memory>4</memory>
      <networkBandwidth>4</networkBandwidth>
      <cost>560</cost>
    </CloudComputer>
    <CloudComputer id="73">
      <id>70</id>
      <cpuPower>3</cpuPower>
      <memory>2</memory>
      <networkBandwidth>2</networkBandwidth>
      <cost>350</cost>
    </CloudComputer>
    <CloudComputer id="74">
      <id>71</id>
      <cpuPower>24</cpuPower>
      <memory>64</memory>
      <networkBandwidth>20</networkBandwidth>
      <cost>4600</cost>
    </CloudComputer>
    <CloudComputer id="75">
      <id>72</id>
      <cpuPower>24</cpuPower>
      <memory>96</memory>
      <networkBandwidth>16</networkBandwidth>
      <cost>4800</cost>
    </CloudComputer>
    <CloudComputer id="76">
      <id>73</id>
      <cpuPower>3</cpuPower>
      <memory>2</memory>
      <networkBandwidth>4</networkBandwidth>
      <cost>450</cost>
    </CloudComputer>
    <CloudComputer id="77">
      <id>74</id>
      <cpuPower>16</cpuPower>
      <memory>96</memory>
      <networkBandwidth>20</networkBandwidth>
      <cost>3000</cost>
    </CloudComputer>
    <CloudComputer id="78">
      <id>75</id>
      <cpuPower>12</cpuPower>
      <memory>16</memory>
      <networkBandwidth>8</networkBandwidth>
      <cost>1100</cost>
    </CloudComputer>
    <CloudComputer id="79">
      <id>76</id>
      <cpuPower>16</cpuPower>
      <memory>64</memory>
      <networkBandwidth>12</networkBandwidth>
      <cost>2200</cost>
    </CloudComputer>
    <CloudComputer id="80">
      <id>77</id>
      <cpuPower>12</cpuPower>
      <memory>32</memory>
      <networkBandwidth>12</networkBandwidth>
      <cost>1400</cost>
    </CloudComputer>
    <CloudComputer id="81">
      <id>78</id>
      <cpuPower>3</cpuPower>
      <memory>2</memory>
      <networkBandwidth>4</networkBandwidth>
      <cost>450</cost>
    </CloudComputer>
    <CloudComputer id="82">
      <id>79</id>
      <cpuPower>6</cpuPower>
      <memory>8</memory>
      <networkBandwidth>4</networkBandwidth>
      <cost>600</cost>
    </CloudComputer>
    <CloudComputer id="83">
      <id>80</id>
      <cpuPower>24</cpuPower>
      <memory>32</memory>
      <networkBandwidth>20</networkBandwidth>
      <cost>4400</cost>
    </CloudComputer>
    <CloudComputer id="84">
      <id>81</id>
      <cpuPower>4</cpuPower>
      <memory>2</memory>
      <networkBandwidth>4</networkBandwidth>
      <cost>480</cost>
    </CloudComputer>
    <CloudComputer id="85">
      <id>82</id>
      <cpuPower>3</cpuPower>
      <memory>2</memory>
      <networkBandwidth>2</networkBandwidth>
      <cost>350</cost>
    </CloudComputer>
    <CloudComputer id="86">
      <id>83</id>
      <cpuPower>6</cpuPower>
      <memory>16</memory>
      <networkBandwidth>8</networkBandwidth>
      <cost>880</cost>
    </CloudComputer>
    <CloudComputer id="87">
      <id>84</id>
      <cpuPower>8</cpuPower>
      <memory>32</memory>
      <networkBandwidth>8</networkBandwidth>
      <cost>1070</cost>
    </CloudComputer>
    <CloudComputer id="88">
      <id>85</id>
      <cpuPower>24</cpuPower>
      <memory>64</memory>
      <networkBandwidth>20</networkBandwidth>
      <cost>4600</cost>
    </CloudComputer>
    <CloudComputer id="89">
      <id>86</id>
      <cpuPower>8</cpuPower>
      <memory>16</memory>
      <networkBandwidth>12</networkBandwidth>
      <cost>1170</cost>
    </CloudComputer>
    <CloudComputer id="90">
      <id>87</id>
      <cpuPower>8</cpuPower>
      <memory>16</memory>
      <networkBandwidth>8</networkBandwidth>
      <cost>970</cost>
    </CloudComputer>
    <CloudComputer id="91">
      <id>88</id>
      <cpuPower>16</cpuPower>
      <memory>64</memory>
      <networkBandwidth>20</networkBandwidth>
      <cost>2600</cost>
    </CloudComputer>
    <CloudComputer id="92">
      <id>89</id>
      <cpuPower>24</cpuPower>
      <memory>64</memory>
      <networkBandwidth>16</networkBandwidth>
      <cost>4400</cost>
    </CloudComputer>
    <CloudComputer id="93">
      <id>90</id>
      <cpuPower>8</cpuPower>
      <memory>8</memory>
      <networkBandwidth>8</networkBandwidth>
      <cost>890</cost>
    </CloudComputer>
    <CloudComputer id="94">
      <id>91</id>
      <cpuPower>8</cpuPower>
      <memory>32</memory>
      <networkBandwidth>8</networkBandwidth>
      <cost>1070</cost>
    </CloudComputer>
    <CloudComputer id="95">
      <id>92</id>
      <cpuPower>24</cpuPower>
      <memory>96</memory>
      <networkBandwidth>20</networkBandwidth>
      <cost>5000</cost>
    </CloudComputer>
    <CloudComputer id="96">
      <id>93</id>
      <cpuPower>8</cpuPower>
      <memory>32</memory>
      <networkBandwidth>8</networkBandwidth>
      <cost>1070</cost>
    </CloudComputer>
    <CloudComputer id="97">
      <id>94</id>
      <cpuPower>3</cpuPower>
      <memory>2</memory>
      <networkBandwidth>4</networkBandwidth>
      <cost>450</cost>
    </CloudComputer>
    <CloudComputer id="98">
      <id>95</id>
      <cpuPower>12</cpuPower>
      <memory>16</memory>
      <networkBandwidth>6</networkBandwidth>
      <cost>1000</cost>
    </CloudComputer>
    <CloudComputer id="99">
      <id>96</id>
      <cpuPower>3</cpuPower>
      <memory>2</memory>
      <networkBandwidth>2</networkBandwidth>
      <cost>350</cost>
    </CloudComputer>
    <CloudComputer id="100">
      <id>97</id>
      <cpuPower>4</cpuPower>
      <memory>8</memory>
      <networkBandwidth>4</networkBandwidth>
      <cost>560</cost>
    </CloudComputer>
    <CloudComputer id="101">
      <id>98</id>
      <cpuPower>8</cpuPower>
      <memory>16</memory>
      <networkBandwidth>8</networkBandwidth>
      <cost>970</cost>
    </CloudComputer>
    <CloudComputer id="102">
      <id>99</id>
      <cpuPower>3</cpuPower>
      <memory>2</memory>
      <networkBandwidth>2</networkBandwidth>
      <cost>350</cost>
    </CloudComputer>
  </computerList>
  <processList id="103">
    <CloudProcess id="104">
      <id>0</id>
      <requiredCpuPower>3</requiredCpuPower>
      <requiredMemory>2</requiredMemory>
      <requiredNetworkBandwidth>1</requiredNetworkBandwidth>
    </CloudProcess>
    <CloudProcess id="105">
      <id>1</id>
      <requiredCpuPower>1</requiredCpuPower>
      <requiredMemory>1</requiredMemory>
      <requiredNetworkBandwidth>5</requiredNetworkBandwidth>
    </CloudProcess>
    <CloudProcess id="106">
      <id>2</id>
      <requiredCpuPower>1</requiredCpuPower>
      <requiredMemory>1</requiredMemory>
      <requiredNetworkBandwidth>1</requiredNetworkBandwidth>
    </CloudProcess>
    <CloudProcess id="107">
      <id>3</id>
      <requiredCpuPower>1</requiredCpuPower>
      <requiredMemory>3</requiredMemory>
      <requiredNetworkBandwidth>1</requiredNetworkBandwidth>
    </CloudProcess>
    <CloudProcess id="108">
      <id>4</id>
      <requiredCpuPower>1</requiredCpuPower>
      <requiredMemory>1</requiredMemory>
      <requiredNetworkBandwidth>1</requiredNetworkBandwidth>
    </CloudProcess>
    <CloudProcess id="109">
      <id>5</id>
      <requiredCpuPower>8</requiredCpuPower>
      <requiredMemory>1</requiredMemory>
      <requiredNetworkBandwidth>5</requiredNetworkBandwidth>
    </CloudProcess>
    <CloudProcess id="110">
      <id>6</id>
      <requiredCpuPower>1</requiredCpuPower>
      <requiredMemory>1</requiredMemory>
      <requiredNetworkBandwidth>1</requiredNetworkBandwidth>
    </CloudProcess>
    <CloudProcess id="111">
      <id>7</id>
      <requiredCpuPower>3</requiredCpuPower>
      <requiredMemory>1</requiredMemory>
      <requiredNetworkBandwidth>1</requiredNetworkBandwidth>
    </CloudProcess>
    <CloudProcess id="112">
      <id>8</id>
      <requiredCpuPower>1</requiredCpuPower>
      <requiredMemory>1</requiredMemory>
      <requiredNetworkBandwidth>1</requiredNetworkBandwidth>
    </CloudProcess>
    <CloudProcess id="113">
      <id>9</id>
      <requiredCpuPower>1</requiredCpuPower>
      <requiredMemory>1</requiredMemory>
      <requiredNetworkBandwidth>1</requiredNetworkBandwidth>
    </CloudProcess>
    <CloudProcess id="114">
      <id>10</id>
      <requiredCpuPower>9</requiredCpuPower>
      <requiredMemory>4</requiredMemory>
      <requiredNetworkBandwidth>5</requiredNetworkBandwidth>
    </CloudProcess>
    <CloudProcess id="115">
      <id>11</id>
      <requiredCpuPower>10</requiredCpuPower>
      <requiredMemory>1</requiredMemory>
      <requiredNetworkBandwidth>1</requiredNetworkBandwidth>
    </CloudProcess>
    <CloudProcess id="116">
      <id>12</id>
      <requiredCpuPower>2</requiredCpuPower>
      <requiredMemory>1</requiredMemory>
      <requiredNetworkBandwidth>1</requiredNetworkBandwidth>
    </CloudProcess>
    <CloudProcess id="117">
      <id>13</id>
      <requiredCpuPower>1</requiredCpuPower>
      <requiredMemory>1</requiredMemory>
      <requiredNetworkBandwidth>1</requiredNetworkBandwidth>
    </CloudProcess>
    <CloudProcess id="118">
      <id>14</id>
      <requiredCpuPower>1</requiredCpuPower>
      <requiredMemory>1</requiredMemory>
      <requiredNetworkBandwidth>1</requiredNetworkBandwidth>
    </CloudProcess>
    <CloudProcess id="119">
      <id>15</id>
      <requiredCpuPower>1</requiredCpuPower>
      <requiredMemory>1</requiredMemory>
      <requiredNetworkBandwidth>6</requiredNetworkBandwidth>
    </CloudProcess>
    <CloudProcess id="120">
      <id>16</id>
      <requiredCpuPower>2</requiredCpuPower>
      <requiredMemory>23</requiredMemory>
      <requiredNetworkBandwidth>1</requiredNetworkBandwidth>
    </CloudProcess>
    <CloudProcess id="121">
      <id>17</id>
      <requiredCpuPower>1</requiredCpuPower>
      <requiredMemory>1</requiredMemory>
      <requiredNetworkBandwidth>2</requiredNetworkBandwidth>
    </CloudProcess>
    <CloudProcess id="122">
      <id>18</id>
      <requiredCpuPower>1</requiredCpuPower>
      <requiredMemory>4</requiredMemory>
      <requiredNetworkBandwidth>1</requiredNetworkBandwidth>
    </CloudProcess>
    <CloudProcess id="123">
      <id>19</id>
      <requiredCpuPower>10</requiredCpuPower>
      <requiredMemory>14</requiredMemory>
      <requiredNetworkBandwidth>1</requiredNetworkBandwidth>
    </CloudProcess>
    <CloudProcess id="124">
      <id>20</id>
      <requiredCpuPower>2</requiredCpuPower>
      <requiredMemory>1</requiredMemory>
      <requiredNetworkBandwidth>1</requiredNetworkBandwidth>
    </CloudProcess>
    <CloudProcess id="125">
      <id>21</id>
      <requiredCpuPower>2</requiredCpuPower>
      <requiredMemory>1</requiredMemory>
      <requiredNetworkBandwidth>5</requiredNetworkBandwidth>
    </CloudProcess>
    <CloudProcess id="126">
      <id>22</id>
      <requiredCpuPower>2</requiredCpuPower>
      <requiredMemory>1</requiredMemory>
      <requiredNetworkBandwidth>1</requiredNetworkBandwidth>
    </CloudProcess>
    <CloudProcess id="127">
      <id>23</id>
      <requiredCpuPower>6</requiredCpuPower>
      <requiredMemory>1</requiredMemory>
      <requiredNetworkBandwidth>1</requiredNetworkBandwidth>
    </CloudProcess>
    <CloudProcess id="128">
      <id>24</id>
      <requiredCpuPower>12</requiredCpuPower>
      <requiredMemory>18</requiredMemory>
      <requiredNetworkBandwidth>9</requiredNetworkBandwidth>
    </CloudProcess>
    <CloudProcess id="129">
      <id>25</id>
      <requiredCpuPower>1</requiredCpuPower>
      <requiredMemory>22</requiredMemory>
      <requiredNetworkBandwidth>1</requiredNetworkBandwidth>
    </CloudProcess>
    <CloudProcess id="130">
      <id>26</id>
      <requiredCpuPower>1</requiredCpuPower>
      <requiredMemory>1</requiredMemory>
      <requiredNetworkBandwidth>11</requiredNetworkBandwidth>
    </CloudProcess>
    <CloudProcess id="131">
      <id>27</id>
      <requiredCpuPower>3</requiredCpuPower>
      <requiredMemory>1</requiredMemory>
      <requiredNetworkBandwidth>1</requiredNetworkBandwidth>
    </CloudProcess>
    <CloudProcess id="132">
      <id>28</id>
      <requiredCpuPower>1</requiredCpuPower>
      <requiredMemory>13</requiredMemory>
      <requiredNetworkBandwidth>1</requiredNetworkBandwidth>
    </CloudProcess>
    <CloudProcess id="133">
      <id>29</id>
      <requiredCpuPower>5</requiredCpuPower>
      <requiredMemory>1</requiredMemory>
      <requiredNetworkBandwidth>1</requiredNetworkBandwidth>
    </CloudProcess>
    <CloudProcess id="134">
      <id>30</id>
      <requiredCpuPower>1</requiredCpuPower>
      <requiredMemory>3</requiredMemory>
      <requiredNetworkBandwidth>1</requiredNetworkBandwidth>
    </CloudProcess>
    <CloudProcess id="135">
      <id>31</id>
      <requiredCpuPower>1</requiredCpuPower>
      <requiredMemory>5</requiredMemory>
      <requiredNetworkBandwidth>1</requiredNetworkBandwidth>
    </CloudProcess>
    <CloudProcess id="136">
      <id>32</id>
      <requiredCpuPower>1</requiredCpuPower>
      <requiredMemory>1</requiredMemory>
      <requiredNetworkBandwidth>3</requiredNetworkBandwidth>
    </CloudProcess>
    <CloudProcess id="137">
      <id>33</id>
      <requiredCpuPower>1</requiredCpuPower>
      <requiredMemory>22</requiredMemory>
      <requiredNetworkBandwidth>3</requiredNetworkBandwidth>
    </CloudProcess>
    <CloudProcess id="138">
      <id>34</id>
      <requiredCpuPower>1</requiredCpuPower>
      <requiredMemory>24</requiredMemory>
      <requiredNetworkBandwidth>1</requiredNetworkBandwidth>
    </CloudProcess>
    <CloudProcess id="139">
      <id>35</id>
      <requiredCpuPower>1</requiredCpuPower>
      <requiredMemory>1</requiredMemory>
      <requiredNetworkBandwidth>1</requiredNetworkBandwidth>
    </CloudProcess>
    <CloudProcess id="140">
      <id>36</id>
      <requiredCpuPower>1</requiredCpuPower>
      <requiredMemory>1</requiredMemory>
      <requiredNetworkBandwidth>3</requiredNetworkBandwidth>
    </CloudProcess>
    <CloudProcess id="141">
      <id>37</id>
      <requiredCpuPower>1</requiredCpuPower>
      <requiredMemory>1</requiredMemory>
      <requiredNetworkBandwidth>1</requiredNetworkBandwidth>
    </CloudProcess>
    <CloudProcess id="142">
      <id>38</id>
      <requiredCpuPower>1</requiredCpuPower>
      <requiredMemory>2</requiredMemory>
      <requiredNetworkBandwidth>1</requiredNetworkBandwidth>
    </CloudProcess>
    <CloudProcess id="143">
      <id>39</id>
      <requiredCpuPower>1</requiredCpuPower>
      <requiredMemory>1</requiredMemory>
      <requiredNetworkBandwidth>1</requiredNetworkBandwidth>
    </CloudProcess>
    <CloudProcess id="144">
      <id>40</id>
      <requiredCpuPower>1</requiredCpuPower>
      <requiredMemory>1</requiredMemory>
      <requiredNetworkBandwidth>1</requiredNetworkBandwidth>
    </CloudProcess>
    <CloudProcess id="145">
      <id>41</id>
      <requiredCpuPower>1</requiredCpuPower>
      <requiredMemory>1</requiredMemory>
      <requiredNetworkBandwidth>12</requiredNetworkBandwidth>
    </CloudProcess>
    <CloudProcess id="146">
      <id>42</id>
      <requiredCpuPower>1</requiredCpuPower>
      <requiredMemory>3</requiredMemory>
      <requiredNetworkBandwidth>1</requiredNetworkBandwidth>
    </CloudProcess>
    <CloudProcess id="147">
      <id>43</id>
      <requiredCpuPower>7</requiredCpuPower>
      <requiredMemory>1</requiredMemory>
      <requiredNetworkBandwidth>2</requiredNetworkBandwidth>
    </CloudProcess>
    <CloudProcess id="148">
      <id>44</id>
      <requiredCpuPower>1</requiredCpuPower>
      <requiredMemory>1</requiredMemory>
      <requiredNetworkBandwidth>1</requiredNetworkBandwidth>
    </CloudProcess>
    <CloudProcess id="149">
      <id>45</id>
      <requiredCpuPower>5</requiredCpuPower>
      <requiredMemory>10</requiredMemory>
      <requiredNetworkBandwidth>1</requiredNetworkBandwidth>
    </CloudProcess>
    <CloudProcess id="150">
      <id>46</id>
      <requiredCpuPower>1</requiredCpuPower>
      <requiredMemory>2</requiredMemory>
      <requiredNetworkBandwidth>1</requiredNetworkBandwidth>
    </CloudProcess>
    <CloudProcess id="151">
      <id>47</id>
      <requiredCpuPower>1</requiredCpuPower>
      <requiredMemory>1</requiredMemory>
      <requiredNetworkBandwidth>2</requiredNetworkBandwidth>
    </CloudProcess>
    <CloudProcess id="152">
      <id>48</id>
      <requiredCpuPower>1</requiredCpuPower>
      <requiredMemory>25</requiredMemory>
      <requiredNetworkBandwidth>4</requiredNetworkBandwidth>
    </CloudProcess>
    <CloudProcess id="153">
      <id>49</id>
      <requiredCpuPower>3</requiredCpuPower>
      <requiredMemory>2</requiredMemory>
      <requiredNetworkBandwidth>2</requiredNetworkBandwidth>
    </CloudProcess>
    <CloudProcess id="154">
      <id>50</id>
      <requiredCpuPower>1</requiredCpuPower>
      <requiredMemory>30</requiredMemory>
      <requiredNetworkBandwidth>2</requiredNetworkBandwidth>
    </CloudProcess>
    <CloudProcess id="155">
      <id>51</id>
      <requiredCpuPower>1</requiredCpuPower>
      <requiredMemory>1</requiredMemory>
      <requiredNetworkBandwidth>1</requiredNetworkBandwidth>
    </CloudProcess>
    <CloudProcess id="156">
      <id>52</id>
      <requiredCpuPower>1</requiredCpuPower>
      <requiredMemory>28</requiredMemory>
      <requiredNetworkBandwidth>1</requiredNetworkBandwidth>
    </CloudProcess>
    <CloudProcess id="157">
      <id>53</id>
      <requiredCpuPower>1</requiredCpuPower>
      <requiredMemory>1</requiredMemory>
      <requiredNetworkBandwidth>3</requiredNetworkBandwidth>
    </CloudProcess>
    <CloudProcess id="158">
      <id>54</id>
      <requiredCpuPower>2</requiredCpuPower>
      <requiredMemory>5</requiredMemory>
      <requiredNetworkBandwidth>7</requiredNetworkBandwidth>
    </CloudProcess>
    <CloudProcess id="159">
      <id>55</id>
      <requiredCpuPower>1</requiredCpuPower>
      <requiredMemory>6</requiredMemory>
      <requiredNetworkBandwidth>1</requiredNetworkBandwidth>
    </CloudProcess>
    <CloudProcess id="160">
      <id>56</id>
      <requiredCpuPower>1</requiredCpuPower>
      <requiredMemory>1</requiredMemory>
      <requiredNetworkBandwidth>10</requiredNetworkBandwidth>
    </CloudProcess>
    <CloudProcess id="161">
      <id>57</id>
      <requiredCpuPower>3</requiredCpuPower>
      <requiredMemory>4</requiredMemory>
      <requiredNetworkBandwidth>3</requiredNetworkBandwidth>
    </CloudProcess>
    <CloudProcess id="162">
      <id>58</id>
      <requiredCpuPower>2</requiredCpuPower>
      <requiredMemory>1</requiredMemory>
      <requiredNetworkBandwidth>1</requiredNetworkBandwidth>
    </CloudProcess>
    <CloudProcess id="163">
      <id>59</id>
      <requiredCpuPower>1</requiredCpuPower>
      <requiredMemory>1</requiredMemory>
      <requiredNetworkBandwidth>11</requiredNetworkBandwidth>
    </CloudProcess>
    <CloudProcess id="164">
      <id>60</id>
      <requiredCpuPower>1</requiredCpuPower>
      <requiredMemory>16</requiredMemory>
      <requiredNetworkBandwidth>1</requiredNetworkBandwidth>
    </CloudProcess>
    <CloudProcess id="165">
      <id>61</id>
      <requiredCpuPower>1</requiredCpuPower>
      <requiredMemory>1</requiredMemory>
      <requiredNetworkBandwidth>1</requiredNetworkBandwidth>
    </CloudProcess>
    <CloudProcess id="166">
      <id>62</id>
      <requiredCpuPower>1</requiredCpuPower>
      <requiredMemory>1</requiredMemory>
      <requiredNetworkBandwidth>11</requiredNetworkBandwidth>
    </CloudProcess>
    <CloudProcess id="167">
      <id>63</id>
      <requiredCpuPower>1</requiredCpuPower>
      <requiredMemory>18</requiredMemory>
      <requiredNetworkBandwidth>1</requiredNetworkBandwidth>
    </CloudProcess>
    <CloudProcess id="168">
      <id>64</id>
      <requiredCpuPower>11</requiredCpuPower>
      <requiredMemory>2</requiredMemory>
      <requiredNetworkBandwidth>1</requiredNetworkBandwidth>
    </CloudProcess>
    <CloudProcess id="169">
      <id>65</id>
      <requiredCpuPower>1</requiredCpuPower>
      <requiredMemory>19</requiredMemory>
      <requiredNetworkBandwidth>1</requiredNetworkBandwidth>
    </CloudProcess>
    <CloudProcess id="170">
      <id>66</id>
      <requiredCpuPower>1</requiredCpuPower>
      <requiredMemory>1</requiredMemory>
      <requiredNetworkBandwidth>1</requiredNetworkBandwidth>
    </CloudProcess>
    <CloudProcess id="171">
      <id>67</id>
      <requiredCpuPower>1</requiredCpuPower>
      <requiredMemory>1</requiredMemory>
      <requiredNetworkBandwidth>4</requiredNetworkBandwidth>
    </CloudProcess>
    <CloudProcess id="172">
      <id>68</id>
      <requiredCpuPower>10</requiredCpuPower>
      <requiredMemory>4</requiredMemory>
      <requiredNetworkBandwidth>1</requiredNetworkBandwidth>
    </CloudProcess>
    <CloudProcess id="173">
      <id>69</id>
      <requiredCpuPower>1</requiredCpuPower>
      <requiredMemory>2</requiredMemory>
      <requiredNetworkBandwidth>5</requiredNetworkBandwidth>
    </CloudProcess>
    <CloudProcess id="174">
      <id>70</id>
      <requiredCpuPower>1</requiredCpuPower>
      <requiredMemory>3</requiredMemory>
      <requiredNetworkBandwidth>1</requiredNetworkBandwidth>
    </CloudProcess>
    <CloudProcess id="175">
      <id>71</id>
      <requiredCpuPower>6</requiredCpuPower>
      <requiredMemory>1</requiredMemory>
      <requiredNetworkBandwidth>1</requiredNetworkBandwidth>
    </CloudProcess>
    <CloudProcess id="176">
      <id>72</id>
      <requiredCpuPower>1</requiredCpuPower>
      <requiredMemory>1</requiredMemory>
      <requiredNetworkBandwidth>5</requiredNetworkBandwidth>
    </CloudProcess>
    <CloudProcess id="177">
      <id>73</id>
      <requiredCpuPower>3</requiredCpuPower>
      <requiredMemory>3</requiredMemory>
      <requiredNetworkBandwidth>1</requiredNetworkBandwidth>
    </CloudProcess>
    <CloudProcess id="178">
      <id>74</id>
      <requiredCpuPower>1</requiredCpuPower>
      <requiredMemory>32</requiredMemory>
      <requiredNetworkBandwidth>6</requiredNetworkBandwidth>
    </CloudProcess>
    <CloudProcess id="179">
      <id>75</id>
      <requiredCpuPower>8</requiredCpuPower>
      <requiredMemory>1</requiredMemory>
      <requiredNetworkBandwidth>1</requiredNetworkBandwidth>
    </CloudProcess>
    <CloudProcess id="180">
      <id>76</id>
      <requiredCpuPower>1</requiredCpuPower>
      <requiredMemory>1</requiredMemory>
      <requiredNetworkBandwidth>1</requiredNetworkBandwidth>
    </CloudProcess>
    <CloudProcess id="181">
      <id>77</id>
      <requiredCpuPower>1</requiredCpuPower>
      <requiredMemory>8</requiredMemory>
      <requiredNetworkBandwidth>6</requiredNetworkBandwidth>
    </CloudProcess>
    <CloudProcess id="182">
      <id>78</id>
      <requiredCpuPower>3</requiredCpuPower>
      <requiredMemory>1</requiredMemory>
      <requiredNetworkBandwidth>1</requiredNetworkBandwidth>
    </CloudProcess>
    <CloudProcess id="183">
      <id>79</id>
      <requiredCpuPower>2</requiredCpuPower>
      <requiredMemory>1</requiredMemory>
      <requiredNetworkBandwidth>1</requiredNetworkBandwidth>
    </CloudProcess>
    <CloudProcess id="184">
      <id>80</id>
      <requiredCpuPower>1</requiredCpuPower>
      <requiredMemory>1</requiredMemory>
      <requiredNetworkBandwidth>1</requiredNetworkBandwidth>
    </CloudProcess>
    <CloudProcess id="185">
      <id>81</id>
      <requiredCpuPower>1</requiredCpuPower>
      <requiredMemory>10</requiredMemory>
      <requiredNetworkBandwidth>1</requiredNetworkBandwidth>
    </CloudProcess>
    <CloudProcess id="186">
      <id>82</id>
      <requiredCpuPower>7</requiredCpuPower>
      <requiredMemory>24</requiredMemory>
      <requiredNetworkBandwidth>1</requiredNetworkBandwidth>
    </CloudProcess>
    <CloudProcess id="187">
      <id>83</id>
      <requiredCpuPower>1</requiredCpuPower>
      <requiredMemory>18</requiredMemory>
      <requiredNetworkBandwidth>1</requiredNetworkBandwidth>
    </CloudProcess>
    <CloudProcess id="188">
      <id>84</id>
      <requiredCpuPower>1</requiredCpuPower>
      <requiredMemory>16</requiredMemory>
      <requiredNetworkBandwidth>1</requiredNetworkBandwidth>
    </CloudProcess>
    <CloudProcess id="189">
      <id>85</id>
      <requiredCpuPower>6</requiredCpuPower>
      <requiredMemory>19</requiredMemory>
      <requiredNetworkBandwidth>1</requiredNetworkBandwidth>
    </CloudProcess>
    <CloudProcess id="190">
      <id>86</id>
      <requiredCpuPower>2</requiredCpuPower>
      <requiredMemory>1</requiredMemory>
      <requiredNetworkBandwidth>1</requiredNetworkBandwidth>
    </CloudProcess>
    <CloudProcess id="191">
      <id>87</id>
      <requiredCpuPower>1</requiredCpuPower>
      <requiredMemory>1</requiredMemory>
      <requiredNetworkBandwidth>1</requiredNetworkBandwidth>
    </CloudProcess>
    <CloudProcess id="192">
      <id>88</id>
      <requiredCpuPower>1</requiredCpuPower>
      <requiredMemory>1</requiredMemory>
      <requiredNetworkBandwidth>1</requiredNetworkBandwidth>
    </CloudProcess>
    <CloudProcess id="193">
      <id>89</id>
      <requiredCpuPower>1</requiredCpuPower>
      <requiredMemory>14</requiredMemory>
      <requiredNetworkBandwidth>1</requiredNetworkBandwidth>
    </CloudProcess>
    <CloudProcess id="194">
      <id>90</id>
      <requiredCpuPower>1</requiredCpuPower>
      <requiredMemory>1</requiredMemory>
      <requiredNetworkBandwidth>1</requiredNetworkBandwidth>
    </CloudProcess>
    <CloudProcess id="195">
      <id>91</id>
      <requiredCpuPower>2</requiredCpuPower>
      <requiredMemory>6</requiredMemory>
      <requiredNetworkBandwidth>2</requiredNetworkBandwidth>
    </CloudProcess>
    <CloudProcess id="196">
      <id>92</id>
      <requiredCpuPower>1</requiredCpuPower>
      <requiredMemory>1</requiredMemory>
      <requiredNetworkBandwidth>4</requiredNetworkBandwidth>
    </CloudProcess>
    <CloudProcess id="197">
      <id>93</id>
      <requiredCpuPower>1</requiredCpuPower>
      <requiredMemory>1</requiredMemory>
      <requiredNetworkBandwidth>1</requiredNetworkBandwidth>
    </CloudProcess>
    <CloudProcess id="198">
      <id>94</id>
      <requiredCpuPower>1</requiredCpuPower>
      <requiredMemory>2</requiredMemory>
      <requiredNetworkBandwidth>1</requiredNetworkBandwidth>
    </CloudProcess>
    <CloudProcess id="199">
      <id>95</id>
      <requiredCpuPower>1</requiredCpuPower>
      <requiredMemory>1</requiredMemory>
      <requiredNetworkBandwidth>7</requiredNetworkBandwidth>
    </CloudProcess>
    <CloudProcess id="200">
      <id>96</id>
      <requiredCpuPower>3</requiredCpuPower>
      <requiredMemory>3</requiredMemory>
      <requiredNetworkBandwidth>12</requiredNetworkBandwidth>
    </CloudProcess>
    <CloudProcess id="201">
      <id>97</id>
      <requiredCpuPower>1</requiredCpuPower>
      <requiredMemory>1</requiredMemory>
      <requiredNetworkBandwidth>1</requiredNetworkBandwidth>
    </CloudProcess>
    <CloudProcess id="202">
      <id>98</id>
      <requiredCpuPower>2</requiredCpuPower>
      <requiredMemory>5</requiredMemory>
      <requiredNetworkBandwidth>1</requiredNetworkBandwidth>
    </CloudProcess>
    <CloudProcess id="203">
      <id>99</id>
      <requiredCpuPower>1</requiredCpuPower>
      <requiredMemory>1</requiredMemory>
      <requiredNetworkBandwidth>1</requiredNetworkBandwidth>
    </CloudProcess>
    <CloudProcess id="204">
      <id>100</id>
      <requiredCpuPower>1</requiredCpuPower>
      <requiredMemory>1</requiredMemory>
      <requiredNetworkBandwidth>1</requiredNetworkBandwidth>
    </CloudProcess>
    <CloudProcess id="205">
      <id>101</id>
      <requiredCpuPower>1</requiredCpuPower>
      <requiredMemory>1</requiredMemory>
      <requiredNetworkBandwidth>1</requiredNetworkBandwidth>
    </CloudProcess>
    <CloudProcess id="206">
      <id>102</id>
      <requiredCpuPower>1</requiredCpuPower>
      <requiredMemory>1</requiredMemory>
      <requiredNetworkBandwidth>1</requiredNetworkBandwidth>
    </CloudProcess>
    <CloudProcess id="207">
      <id>103</id>
      <requiredCpuPower>2</requiredCpuPower>
      <requiredMemory>1</requiredMemory>
      <requiredNetworkBandwidth>1</requiredNetworkBandwidth>
    </CloudProcess>
    <CloudProcess id="208">
      <id>104</id>
      <requiredCpuPower>1</requiredCpuPower>
      <requiredMemory>3</requiredMemory>
      <requiredNetworkBandwidth>3</requiredNetworkBandwidth>
    </CloudProcess>
    <CloudProcess id="209">
      <id>105</id>
      <requiredCpuPower>1</requiredCpuPower>
      <requiredMemory>1</requiredMemory>
      <requiredNetworkBandwidth>1</requiredNetworkBandwidth>
    </CloudProcess>
    <CloudProcess id="210">
      <id>106</id>
      <requiredCpuPower>10</requiredCpuPower>
      <requiredMemory>1</requiredMemory>
      <requiredNetworkBandwidth>1</requiredNetworkBandwidth>
    </CloudProcess>
    <CloudProcess id="211">
      <id>107</id>
      <requiredCpuPower>1</requiredCpuPower>
      <requiredMemory>1</requiredMemory>
      <requiredNetworkBandwidth>1</requiredNetworkBandwidth>
    </CloudProcess>
    <CloudProcess id="212">
      <id>108</id>
      <requiredCpuPower>1</requiredCpuPower>
      <requiredMemory>25</requiredMemory>
      <requiredNetworkBandwidth>1</requiredNetworkBandwidth>
    </CloudProcess>
    <CloudProcess id="213">
      <id>109</id>
      <requiredCpuPower>1</requiredCpuPower>
      <requiredMemory>1</requiredMemory>
      <requiredNetworkBandwidth>1</requiredNetworkBandwidth>
    </CloudProcess>
    <CloudProcess id="214">
      <id>110</id>
      <requiredCpuPower>1</requiredCpuPower>
      <requiredMemory>1</requiredMemory>
      <requiredNetworkBandwidth>4</requiredNetworkBandwidth>
    </CloudProcess>
    <CloudProcess id="215">
      <id>111</id>
      <requiredCpuPower>1</requiredCpuPower>
      <requiredMemory>1</requiredMemory>
      <requiredNetworkBandwidth>3</requiredNetworkBandwidth>
    </CloudProcess>
    <CloudProcess id="216">
      <id>112</id>
      <requiredCpuPower>9</requiredCpuPower>
      <requiredMemory>1</requiredMemory>
      <requiredNetworkBandwidth>2</requiredNetworkBandwidth>
    </CloudProcess>
    <CloudProcess id="217">
      <id>113</id>
      <requiredCpuPower>1</requiredCpuPower>
      <requiredMemory>1</requiredMemory>
      <requiredNetworkBandwidth>1</requiredNetworkBandwidth>
    </CloudProcess>
    <CloudProcess id="218">
      <id>114</id>
      <requiredCpuPower>4</requiredCpuPower>
      <requiredMemory>7</requiredMemory>
      <requiredNetworkBandwidth>1</requiredNetworkBandwidth>
    </CloudProcess>
    <CloudProcess id="219">
      <id>115</id>
      <requiredCpuPower>1</requiredCpuPower>
      <requiredMemory>1</requiredMemory>
      <requiredNetworkBandwidth>1</requiredNetworkBandwidth>
    </CloudProcess>
    <CloudProcess id="220">
      <id>116</id>
      <requiredCpuPower>1</requiredCpuPower>
      <requiredMemory>7</requiredMemory>
      <requiredNetworkBandwidth>1</requiredNetworkBandwidth>
    </CloudProcess>
    <CloudProcess id="221">
      <id>117</id>
      <requiredCpuPower>2</requiredCpuPower>
      <requiredMemory>1</requiredMemory>
      <requiredNetworkBandwidth>1</requiredNetworkBandwidth>
    </CloudProcess>
    <CloudProcess id="222">
      <id>118</id>
      <requiredCpuPower>1</requiredCpuPower>
      <requiredMemory>3</requiredMemory>
      <requiredNetworkBandwidth>1</requiredNetworkBandwidth>
    </CloudProcess>
    <CloudProcess id="223">
      <id>119</id>
      <requiredCpuPower>1</requiredCpuPower>
      <requiredMemory>1</requiredMemory>
      <requiredNetworkBandwidth>8</requiredNetworkBandwidth>
    </CloudProcess>
    <CloudProcess id="224">
      <id>120</id>
      <requiredCpuPower>2</requiredCpuPower>
      <requiredMemory>2</requiredMemory>
      <requiredNetworkBandwidth>1</requiredNetworkBandwidth>
    </CloudProcess>
    <CloudProcess id="225">
      <id>121</id>
      <requiredCpuPower>2</requiredCpuPower>
      <requiredMemory>3</requiredMemory>
      <requiredNetworkBandwidth>2</requiredNetworkBandwidth>
    </CloudProcess>
    <CloudProcess id="226">
      <id>122</id>
      <requiredCpuPower>4</requiredCpuPower>
      <requiredMemory>1</requiredMemory>
      <requiredNetworkBandwidth>1</requiredNetworkBandwidth>
    </CloudProcess>
    <CloudProcess id="227">
      <id>123</id>
      <requiredCpuPower>1</requiredCpuPower>
      <requiredMemory>1</requiredMemory>
      <requiredNetworkBandwidth>1</requiredNetworkBandwidth>
    </CloudProcess>
    <CloudProcess id="228">
      <id>124</id>
      <requiredCpuPower>1</requiredCpuPower>
      <requiredMemory>3</requiredMemory>
      <requiredNetworkBandwidth>1</requiredNetworkBandwidth>
    </CloudProcess>
    <CloudProcess id="229">
      <id>125</id>
      <requiredCpuPower>1</requiredCpuPower>
      <requiredMemory>8</requiredMemory>
      <requiredNetworkBandwidth>1</requiredNetworkBandwidth>
    </CloudProcess>
    <CloudProcess id="230">
      <id>126</id>
      <requiredCpuPower>1</requiredCpuPower>
      <requiredMemory>12</requiredMemory>
      <requiredNetworkBandwidth>1</requiredNetworkBandwidth>
    </CloudProcess>
    <CloudProcess id="231">
      <id>127</id>
      <requiredCpuPower>8</requiredCpuPower>
      <requiredMemory>1</requiredMemory>
      <requiredNetworkBandwidth>1</requiredNetworkBandwidth>
    </CloudProcess>
    <CloudProcess id="232">
      <id>128</id>
      <requiredCpuPower>1</requiredCpuPower>
      <requiredMemory>1</requiredMemory>
      <requiredNetworkBandwidth>1</requiredNetworkBandwidth>
    </CloudProcess>
    <CloudProcess id="233">
      <id>129</id>
      <requiredCpuPower>4</requiredCpuPower>
      <requiredMemory>3</requiredMemory>
      <requiredNetworkBandwidth>1</requiredNetworkBandwidth>
    </CloudProcess>
    <CloudProcess id="234">
      <id>130</id>
      <requiredCpuPower>2</requiredCpuPower>
      <requiredMemory>1</requiredMemory>
      <requiredNetworkBandwidth>2</requiredNetworkBandwidth>
    </CloudProcess>
    <CloudProcess id="235">
      <id>131</id>
      <requiredCpuPower>1</requiredCpuPower>
      <requiredMemory>1</requiredMemory>
      <requiredNetworkBandwidth>1</requiredNetworkBandwidth>
    </CloudProcess>
    <CloudProcess id="236">
      <id>132</id>
      <requiredCpuPower>9</requiredCpuPower>
      <requiredMemory>1</requiredMemory>
      <requiredNetworkBandwidth>3</requiredNetworkBandwidth>
    </CloudProcess>
    <CloudProcess id="237">
      <id>133</id>
      <requiredCpuPower>1</requiredCpuPower>
      <requiredMemory>1</requiredMemory>
      <requiredNetworkBandwidth>1</requiredNetworkBandwidth>
    </CloudProcess>
    <CloudProcess id="238">
      <id>134</id>
      <requiredCpuPower>1</requiredCpuPower>
      <requiredMemory>1</requiredMemory>
      <requiredNetworkBandwidth>3</requiredNetworkBandwidth>
    </CloudProcess>
    <CloudProcess id="239">
      <id>135</id>
      <requiredCpuPower>1</requiredCpuPower>
      <requiredMemory>1</requiredMemory>
      <requiredNetworkBandwidth>9</requiredNetworkBandwidth>
    </CloudProcess>
    <CloudProcess id="240">
      <id>136</id>
      <requiredCpuPower>1</requiredCpuPower>
      <requiredMemory>1</requiredMemory>
      <requiredNetworkBandwidth>1</requiredNetworkBandwidth>
    </CloudProcess>
    <CloudProcess id="241">
      <id>137</id>
      <requiredCpuPower>1</requiredCpuPower>
      <requiredMemory>1</requiredMemory>
      <requiredNetworkBandwidth>2</requiredNetworkBandwidth>
    </CloudProcess>
    <CloudProcess id="242">
      <id>138</id>
      <requiredCpuPower>7</requiredCpuPower>
      <requiredMemory>8</requiredMemory>
      <requiredNetworkBandwidth>1</requiredNetworkBandwidth>
    </CloudProcess>
    <CloudProcess id="243">
      <id>139</id>
      <requiredCpuPower>12</requiredCpuPower>
      <requiredMemory>1</requiredMemory>
      <requiredNetworkBandwidth>1</requiredNetworkBandwidth>
    </CloudProcess>
    <CloudProcess id="244">
      <id>140</id>
      <requiredCpuPower>1</requiredCpuPower>
      <requiredMemory>1</requiredMemory>
      <requiredNetworkBandwidth>6</requiredNetworkBandwidth>
    </CloudProcess>
    <CloudProcess id="245">
      <id>141</id>
      <requiredCpuPower>1</requiredCpuPower>
      <requiredMemory>3</requiredMemory>
      <requiredNetworkBandwidth>2</requiredNetworkBandwidth>
    </CloudProcess>
    <CloudProcess id="246">
      <id>142</id>
      <requiredCpuPower>2</requiredCpuPower>
      <requiredMemory>1</requiredMemory>
      <requiredNetworkBandwidth>10</requiredNetworkBandwidth>
    </CloudProcess>
    <CloudProcess id="247">
      <id>143</id>
      <requiredCpuPower>1</requiredCpuPower>
      <requiredMemory>1</requiredMemory>
      <requiredNetworkBandwidth>1</requiredNetworkBandwidth>
    </CloudProcess>
    <CloudProcess id="248">
      <id>144</id>
      <requiredCpuPower>1</requiredCpuPower>
      <requiredMemory>1</requiredMemory>
      <requiredNetworkBandwidth>1</requiredNetworkBandwidth>
    </CloudProcess>
    <CloudProcess id="249">
      <id>145</id>
      <requiredCpuPower>1</requiredCpuPower>
      <requiredMemory>3</requiredMemory>
      <requiredNetworkBandwidth>1</requiredNetworkBandwidth>
    </CloudProcess>
    <CloudProcess id="250">
      <id>146</id>
      <requiredCpuPower>7</requiredCpuPower>
      <requiredMemory>27</requiredMemory>
      <requiredNetworkBandwidth>1</requiredNetworkBandwidth>
    </CloudProcess>
    <CloudProcess id="251">
      <id>147</id>
      <requiredCpuPower>1</requiredCpuPower>
      <requiredMemory>9</requiredMemory>
      <requiredNetworkBandwidth>1</requiredNetworkBandwidth>
    </CloudProcess>
    <CloudProcess id="252">
      <id>148</id>
      <requiredCpuPower>1</requiredCpuPower>
      <requiredMemory>9</requiredMemory>
      <requiredNetworkBandwidth>5</requiredNetworkBandwidth>
    </CloudProcess>
    <CloudProcess id="253">
      <id>149</id>
      <requiredCpuPower>1</requiredCpuPower>
      <requiredMemory>1</requiredMemory>
      <requiredNetworkBandwidth>1</requiredNetworkBandwidth>
    </CloudProcess>
    <CloudProcess id="254">
      <id>150</id>
      <requiredCpuPower>2</requiredCpuPower>
      <requiredMemory>4</requiredMemory>
      <requiredNetworkBandwidth>1</requiredNetworkBandwidth>
    </CloudProcess>
    <CloudProcess id="255">
      <id>151</id>
      <requiredCpuPower>1</requiredCpuPower>
      <requiredMemory>1</requiredMemory>
      <requiredNetworkBandwidth>7</requiredNetworkBandwidth>
    </CloudProcess>
    <CloudProcess id="256">
      <id>152</id>
      <requiredCpuPower>1</requiredCpuPower>
      <requiredMemory>10</requiredMemory>
      <requiredNetworkBandwidth>1</requiredNetworkBandwidth>
    </CloudProcess>
    <CloudProcess id="257">
      <id>153</id>
      <requiredCpuPower>2</requiredCpuPower>
      <requiredMemory>2</requiredMemory>
      <requiredNetworkBandwidth>7</requiredNetworkBandwidth>
    </CloudProcess>
    <CloudProcess id="258">
      <id>154</id>
      <requiredCpuPower>1</requiredCpuPower>
      <requiredMemory>1</requiredMemory>
      <requiredNetworkBandwidth>1</requiredNetworkBandwidth>
    </CloudProcess>
    <CloudProcess id="259">
      <id>155</id>
      <requiredCpuPower>7</requiredCpuPower>
      <requiredMemory>3</requiredMemory>
      <requiredNetworkBandwidth>7</requiredNetworkBandwidth>
    </CloudProcess>
    <CloudProcess id="260">
      <id>156</id>
      <requiredCpuPower>1</requiredCpuPower>
      <requiredMemory>2</requiredMemory>
      <requiredNetworkBandwidth>1</requiredNetworkBandwidth>
    </CloudProcess>
    <CloudProcess id="261">
      <id>157</id>
      <requiredCpuPower>1</requiredCpuPower>
      <requiredMemory>24</requiredMemory>
      <requiredNetworkBandwidth>1</requiredNetworkBandwidth>
    </CloudProcess>
    <CloudProcess id="262">
      <id>158</id>
      <requiredCpuPower>1</requiredCpuPower>
      <requiredMemory>1</requiredMemory>
      <requiredNetworkBandwidth>1</requiredNetworkBandwidth>
    </CloudProcess>
    <CloudProcess id="263">
      <id>159</id>
      <requiredCpuPower>1</requiredCpuPower>
      <requiredMemory>2</requiredMemory>
      <requiredNetworkBandwidth>1</requiredNetworkBandwidth>
    </CloudProcess>
    <CloudProcess id="264">
      <id>160</id>
      <requiredCpuPower>1</requiredCpuPower>
      <requiredMemory>13</requiredMemory>
      <requiredNetworkBandwidth>1</requiredNetworkBandwidth>
    </CloudProcess>
    <CloudProcess id="265">
      <id>161</id>
      <requiredCpuPower>1</requiredCpuPower>
      <requiredMemory>1</requiredMemory>
      <requiredNetworkBandwidth>1</requiredNetworkBandwidth>
    </CloudProcess>
    <CloudProcess id="266">
      <id>162</id>
      <requiredCpuPower>1</requiredCpuPower>
      <requiredMemory>1</requiredMemory>
      <requiredNetworkBandwidth>12</requiredNetworkBandwidth>
    </CloudProcess>
    <CloudProcess id="267">
      <id>163</id>
      <requiredCpuPower>1</requiredCpuPower>
      <requiredMemory>1</requiredMemory>
      <requiredNetworkBandwidth>1</requiredNetworkBandwidth>
    </CloudProcess>
    <CloudProcess id="268">
      <id>164</id>
      <requiredCpuPower>1</requiredCpuPower>
      <requiredMemory>21</requiredMemory>
      <requiredNetworkBandwidth>2</requiredNetworkBandwidth>
    </CloudProcess>
    <CloudProcess id="269">
      <id>165</id>
      <requiredCpuPower>1</requiredCpuPower>
      <requiredMemory>1</requiredMemory>
      <requiredNetworkBandwidth>2</requiredNetworkBandwidth>
    </CloudProcess>
    <CloudProcess id="270">
      <id>166</id>
      <requiredCpuPower>1</requiredCpuPower>
      <requiredMemory>10</requiredMemory>
      <requiredNetworkBandwidth>1</requiredNetworkBandwidth>
    </CloudProcess>
    <CloudProcess id="271">
      <id>167</id>
      <requiredCpuPower>4</requiredCpuPower>
      <requiredMemory>2</requiredMemory>
      <requiredNetworkBandwidth>1</requiredNetworkBandwidth>
    </CloudProcess>
    <CloudProcess id="272">
      <id>168</id>
      <requiredCpuPower>3</requiredCpuPower>
      <requiredMemory>7</requiredMemory>
      <requiredNetworkBandwidth>1</requiredNetworkBandwidth>
    </CloudProcess>
    <CloudProcess id="273">
      <id>169</id>
      <requiredCpuPower>1</requiredCpuPower>
      <requiredMemory>1</requiredMemory>
      <requiredNetworkBandwidth>1</requiredNetworkBandwidth>
    </CloudProcess>
    <CloudProcess id="274">
      <id>170</id>
      <requiredCpuPower>3</requiredCpuPower>
      <requiredMemory>31</requiredMemory>
      <requiredNetworkBandwidth>1</requiredNetworkBandwidth>
    </CloudProcess>
    <CloudProcess id="275">
      <id>171</id>
      <requiredCpuPower>1</requiredCpuPower>
      <requiredMemory>1</requiredMemory>
      <requiredNetworkBandwidth>1</requiredNetworkBandwidth>
    </CloudProcess>
    <CloudProcess id="276">
      <id>172</id>
      <requiredCpuPower>1</requiredCpuPower>
      <requiredMemory>1</requiredMemory>
      <requiredNetworkBandwidth>1</requiredNetworkBandwidth>
    </CloudProcess>
    <CloudProcess id="277">
      <id>173</id>
      <requiredCpuPower>1</requiredCpuPower>
      <requiredMemory>1</requiredMemory>
      <requiredNetworkBandwidth>1</requiredNetworkBandwidth>
    </CloudProcess>
    <CloudProcess id="278">
      <id>174</id>
      <requiredCpuPower>3</requiredCpuPower>
      <requiredMemory>1</requiredMemory>
      <requiredNetworkBandwidth>1</requiredNetworkBandwidth>
    </CloudProcess>
    <CloudProcess id="279">
      <id>175</id>
      <requiredCpuPower>1</requiredCpuPower>
      <requiredMemory>9</requiredMemory>
      <requiredNetworkBandwidth>1</requiredNetworkBandwidth>
    </CloudProcess>
    <CloudProcess id="280">
      <id>176</id>
      <requiredCpuPower>1</requiredCpuPower>
      <requiredMemory>18</requiredMemory>
      <requiredNetworkBandwidth>4</requiredNetworkBandwidth>
    </CloudProcess>
    <CloudProcess id="281">
      <id>177</id>
      <requiredCpuPower>1</requiredCpuPower>
      <requiredMemory>8</requiredMemory>
      <requiredNetworkBandwidth>2</requiredNetworkBandwidth>
    </CloudProcess>
    <CloudProcess id="282">
      <id>178</id>
      <requiredCpuPower>1</requiredCpuPower>
      <requiredMemory>1</requiredMemory>
      <requiredNetworkBandwidth>1</requiredNetworkBandwidth>
    </CloudProcess>
    <CloudProcess id="283">
      <id>179</id>
      <requiredCpuPower>4</requiredCpuPower>
      <requiredMemory>1</requiredMemory>
      <requiredNetworkBandwidth>1</requiredNetworkBandwidth>
    </CloudProcess>
    <CloudProcess id="284">
      <id>180</id>
      <requiredCpuPower>1</requiredCpuPower>
      <requiredMemory>1</requiredMemory>
      <requiredNetworkBandwidth>1</requiredNetworkBandwidth>
    </CloudProcess>
    <CloudProcess id="285">
      <id>181</id>
      <requiredCpuPower>1</requiredCpuPower>
      <requiredMemory>1</requiredMemory>
      <requiredNetworkBandwidth>1</requiredNetworkBandwidth>
    </CloudProcess>
    <CloudProcess id="286">
      <id>182</id>
      <requiredCpuPower>6</requiredCpuPower>
      <requiredMemory>1</requiredMemory>
      <requiredNetworkBandwidth>1</requiredNetworkBandwidth>
    </CloudProcess>
    <CloudProcess id="287">
      <id>183</id>
      <requiredCpuPower>1</requiredCpuPower>
      <requiredMemory>1</requiredMemory>
      <requiredNetworkBandwidth>2</requiredNetworkBandwidth>
    </CloudProcess>
    <CloudProcess id="288">
      <id>184</id>
      <requiredCpuPower>9</requiredCpuPower>
      <requiredMemory>1</requiredMemory>
      <requiredNetworkBandwidth>2</requiredNetworkBandwidth>
    </CloudProcess>
    <CloudProcess id="289">
      <id>185</id>
      <requiredCpuPower>1</requiredCpuPower>
      <requiredMemory>1</requiredMemory>
      <requiredNetworkBandwidth>10</requiredNetworkBandwidth>
    </CloudProcess>
    <CloudProcess id="290">
      <id>186</id>
      <requiredCpuPower>8</requiredCpuPower>
      <requiredMemory>2</requiredMemory>
      <requiredNetworkBandwidth>1</requiredNetworkBandwidth>
    </CloudProcess>
    <CloudProcess id="291">
      <id>187</id>
      <requiredCpuPower>1</requiredCpuPower>
      <requiredMemory>1</requiredMemory>
      <requiredNetworkBandwidth>1</requiredNetworkBandwidth>
    </CloudProcess>
    <CloudProcess id="292">
      <id>188</id>
      <requiredCpuPower>1</requiredCpuPower>
      <requiredMemory>1</requiredMemory>
      <requiredNetworkBandwidth>1</requiredNetworkBandwidth>
    </CloudProcess>
    <CloudProcess id="293">
      <id>189</id>
      <requiredCpuPower>1</requiredCpuPower>
      <requiredMemory>10</requiredMemory>
      <requiredNetworkBandwidth>1</requiredNetworkBandwidth>
    </CloudProcess>
    <CloudProcess id="294">
      <id>190</id>
      <requiredCpuPower>1</requiredCpuPower>
      <requiredMemory>1</requiredMemory>
      <requiredNetworkBandwidth>1</requiredNetworkBandwidth>
    </CloudProcess>
    <CloudProcess id="295">
      <id>191</id>
      <requiredCpuPower>1</requiredCpuPower>
      <requiredMemory>2</requiredMemory>
      <requiredNetworkBandwidth>1</requiredNetworkBandwidth>
    </CloudProcess>
    <CloudProcess id="296">
      <id>192</id>
      <requiredCpuPower>1</requiredCpuPower>
      <requiredMemory>1</requiredMemory>
      <requiredNetworkBandwidth>2</requiredNetworkBandwidth>
    </CloudProcess>
    <CloudProcess id="297">
      <id>193</id>
      <requiredCpuPower>1</requiredCpuPower>
      <requiredMemory>1</requiredMemory>
      <requiredNetworkBandwidth>1</requiredNetworkBandwidth>
    </CloudProcess>
    <CloudProcess id="298">
      <id>194</id>
      <requiredCpuPower>5</requiredCpuPower>
      <requiredMemory>1</requiredMemory>
      <requiredNetworkBandwidth>2</requiredNetworkBandwidth>
    </CloudProcess>
    <CloudProcess id="299">
      <id>195</id>
      <requiredCpuPower>1</requiredCpuPower>
      <requiredMemory>1</requiredMemory>
      <requiredNetworkBandwidth>1</requiredNetworkBandwidth>
    </CloudProcess>
    <CloudProcess id="300">
      <id>196</id>
      <requiredCpuPower>1</requiredCpuPower>
      <requiredMemory>1</requiredMemory>
      <requiredNetworkBandwidth>2</requiredNetworkBandwidth>
    </CloudProcess>
    <CloudProcess id="301">
      <id>197</id>
      <requiredCpuPower>3</requiredCpuPower>
      <requiredMemory>2</requiredMemory>
      <requiredNetworkBandwidth>1</requiredNetworkBandwidth>
    </CloudProcess>
    <CloudProcess id="302">
      <id>198</id>
      <requiredCpuPower>1</requiredCpuPower>
      <requiredMemory>1</requiredMemory>
      <requiredNetworkBandwidth>5</requiredNetworkBandwidth>
    </CloudProcess>
    <CloudProcess id="303">
      <id>199</id>
      <requiredCpuPower>1</requiredCpuPower>
      <requiredMemory>4</requiredMemory>
      <requiredNetworkBandwidth>3</requiredNetworkBandwidth>
    </CloudProcess>
    <CloudProcess id="304">
      <id>200</id>
      <requiredCpuPower>1</requiredCpuPower>
      <requiredMemory>4</requiredMemory>
      <requiredNetworkBandwidth>1</requiredNetworkBandwidth>
    </CloudProcess>
    <CloudProcess id="305">
      <id>201</id>
      <requiredCpuPower>1</requiredCpuPower>
      <requiredMemory>3</requiredMemory>
      <requiredNetworkBandwidth>1</requiredNetworkBandwidth>
    </CloudProcess>
    <CloudProcess id="306">
      <id>202</id>
      <requiredCpuPower>1</requiredCpuPower>
      <requiredMemory>15</requiredMemory>
      <requiredNetworkBandwidth>1</requiredNetworkBandwidth>
    </CloudProcess>
    <CloudProcess id="307">
      <id>203</id>
      <requiredCpuPower>1</requiredCpuPower>
      <requiredMemory>21</requiredMemory>
      <requiredNetworkBandwidth>1</requiredNetworkBandwidth>
    </CloudProcess>
    <CloudProcess id="308">
      <id>204</id>
      <requiredCpuPower>1</requiredCpuPower>
      <requiredMemory>21</requiredMemory>
      <requiredNetworkBandwidth>10</requiredNetworkBandwidth>
    </CloudProcess>
    <CloudProcess id="309">
      <id>205</id>
      <requiredCpuPower>1</requiredCpuPower>
      <requiredMemory>1</requiredMemory>
      <requiredNetworkBandwidth>1</requiredNetworkBandwidth>
    </CloudProcess>
    <CloudProcess id="310">
      <id>206</id>
      <requiredCpuPower>9</requiredCpuPower>
      <requiredMemory>1</requiredMemory>
      <requiredNetworkBandwidth>10</requiredNetworkBandwidth>
    </CloudProcess>
    <CloudProcess id="311">
      <id>207</id>
      <requiredCpuPower>1</requiredCpuPower>
      <requiredMemory>1</requiredMemory>
      <requiredNetworkBandwidth>1</requiredNetworkBandwidth>
    </CloudProcess>
    <CloudProcess id="312">
      <id>208</id>
      <requiredCpuPower>1</requiredCpuPower>
      <requiredMemory>1</requiredMemory>
      <requiredNetworkBandwidth>1</requiredNetworkBandwidth>
    </CloudProcess>
    <CloudProcess id="313">
      <id>209</id>
      <requiredCpuPower>1</requiredCpuPower>
      <requiredMemory>2</requiredMemory>
      <requiredNetworkBandwidth>1</requiredNetworkBandwidth>
    </CloudProcess>
    <CloudProcess id="314">
      <id>210</id>
      <requiredCpuPower>4</requiredCpuPower>
      <requiredMemory>2</requiredMemory>
      <requiredNetworkBandwidth>1</requiredNetworkBandwidth>
    </CloudProcess>
    <CloudProcess id="315">
      <id>211</id>
      <requiredCpuPower>3</requiredCpuPower>
      <requiredMemory>6</requiredMemory>
      <requiredNetworkBandwidth>2</requiredNetworkBandwidth>
    </CloudProcess>
    <CloudProcess id="316">
      <id>212</id>
      <requiredCpuPower>1</requiredCpuPower>
      <requiredMemory>2</requiredMemory>
      <requiredNetworkBandwidth>2</requiredNetworkBandwidth>
    </CloudProcess>
    <CloudProcess id="317">
      <id>213</id>
      <requiredCpuPower>1</requiredCpuPower>
      <requiredMemory>7</requiredMemory>
      <requiredNetworkBandwidth>1</requiredNetworkBandwidth>
    </CloudProcess>
    <CloudProcess id="318">
      <id>214</id>
      <requiredCpuPower>1</requiredCpuPower>
      <requiredMemory>1</requiredMemory>
      <requiredNetworkBandwidth>1</requiredNetworkBandwidth>
    </CloudProcess>
    <CloudProcess id="319">
      <id>215</id>
      <requiredCpuPower>1</requiredCpuPower>
      <requiredMemory>2</requiredMemory>
      <requiredNetworkBandwidth>1</requiredNetworkBandwidth>
    </CloudProcess>
    <CloudProcess id="320">
      <id>216</id>
      <requiredCpuPower>1</requiredCpuPower>
      <requiredMemory>30</requiredMemory>
      <requiredNetworkBandwidth>3</requiredNetworkBandwidth>
    </CloudProcess>
    <CloudProcess id="321">
      <id>217</id>
      <requiredCpuPower>1</requiredCpuPower>
      <requiredMemory>1</requiredMemory>
      <requiredNetworkBandwidth>1</requiredNetworkBandwidth>
    </CloudProcess>
    <CloudProcess id="322">
      <id>218</id>
      <requiredCpuPower>1</requiredCpuPower>
      <requiredMemory>25</requiredMemory>
      <requiredNetworkBandwidth>4</requiredNetworkBandwidth>
    </CloudProcess>
    <CloudProcess id="323">
      <id>219</id>
      <requiredCpuPower>1</requiredCpuPower>
      <requiredMemory>1</requiredMemory>
      <requiredNetworkBandwidth>12</requiredNetworkBandwidth>
    </CloudProcess>
    <CloudProcess id="324">
      <id>220</id>
      <requiredCpuPower>8</requiredCpuPower>
      <requiredMemory>1</requiredMemory>
      <requiredNetworkBandwidth>1</requiredNetworkBandwidth>
    </CloudProcess>
    <CloudProcess id="325">
      <id>221</id>
      <requiredCpuPower>1</requiredCpuPower>
      <requiredMemory>1</requiredMemory>
      <requiredNetworkBandwidth>4</requiredNetworkBandwidth>
    </CloudProcess>
    <CloudProcess id="326">
      <id>222</id>
      <requiredCpuPower>1</requiredCpuPower>
      <requiredMemory>2</requiredMemory>
      <requiredNetworkBandwidth>1</requiredNetworkBandwidth>
    </CloudProcess>
    <CloudProcess id="327">
      <id>223</id>
      <requiredCpuPower>4</requiredCpuPower>
      <requiredMemory>8</requiredMemory>
      <requiredNetworkBandwidth>2</requiredNetworkBandwidth>
    </CloudProcess>
    <CloudProcess id="328">
      <id>224</id>
      <requiredCpuPower>1</requiredCpuPower>
      <requiredMemory>1</requiredMemory>
      <requiredNetworkBandwidth>1</requiredNetworkBandwidth>
    </CloudProcess>
    <CloudProcess id="329">
      <id>225</id>
      <requiredCpuPower>1</requiredCpuPower>
      <requiredMemory>31</requiredMemory>
      <requiredNetworkBandwidth>1</requiredNetworkBandwidth>
    </CloudProcess>
    <CloudProcess id="330">
      <id>226</id>
      <requiredCpuPower>1</requiredCpuPower>
      <requiredMemory>1</requiredMemory>
      <requiredNetworkBandwidth>1</requiredNetworkBandwidth>
    </CloudProcess>
    <CloudProcess id="331">
      <id>227</id>
      <requiredCpuPower>1</requiredCpuPower>
      <requiredMemory>1</requiredMemory>
      <requiredNetworkBandwidth>2</requiredNetworkBandwidth>
    </CloudProcess>
    <CloudProcess id="332">
      <id>228</id>
      <requiredCpuPower>1</requiredCpuPower>
      <requiredMemory>1</requiredMemory>
      <requiredNetworkBandwidth>1</requiredNetworkBandwidth>
    </CloudProcess>
    <CloudProcess id="333">
      <id>229</id>
      <requiredCpuPower>1</requiredCpuPower>
      <requiredMemory>1</requiredMemory>
      <requiredNetworkBandwidth>4</requiredNetworkBandwidth>
    </CloudProcess>
    <CloudProcess id="334">
      <id>230</id>
      <requiredCpuPower>1</requiredCpuPower>
      <requiredMemory>6</requiredMemory>
      <requiredNetworkBandwidth>3</requiredNetworkBandwidth>
    </CloudProcess>
    <CloudProcess id="335">
      <id>231</id>
      <requiredCpuPower>1</requiredCpuPower>
      <requiredMemory>1</requiredMemory>
      <requiredNetworkBandwidth>3</requiredNetworkBandwidth>
    </CloudProcess>
    <CloudProcess id="336">
      <id>232</id>
      <requiredCpuPower>6</requiredCpuPower>
      <requiredMemory>1</requiredMemory>
      <requiredNetworkBandwidth>1</requiredNetworkBandwidth>
    </CloudProcess>
    <CloudProcess id="337">
      <id>233</id>
      <requiredCpuPower>1</requiredCpuPower>
      <requiredMemory>21</requiredMemory>
      <requiredNetworkBandwidth>5</requiredNetworkBandwidth>
    </CloudProcess>
    <CloudProcess id="338">
      <id>234</id>
      <requiredCpuPower>3</requiredCpuPower>
      <requiredMemory>1</requiredMemory>
      <requiredNetworkBandwidth>1</requiredNetworkBandwidth>
    </CloudProcess>
    <CloudProcess id="339">
      <id>235</id>
      <requiredCpuPower>7</requiredCpuPower>
      <requiredMemory>1</requiredMemory>
      <requiredNetworkBandwidth>7</requiredNetworkBandwidth>
    </CloudProcess>
    <CloudProcess id="340">
      <id>236</id>
      <requiredCpuPower>1</requiredCpuPower>
      <requiredMemory>7</requiredMemory>
      <requiredNetworkBandwidth>7</requiredNetworkBandwidth>
    </CloudProcess>
    <CloudProcess id="341">
      <id>237</id>
      <requiredCpuPower>1</requiredCpuPower>
      <requiredMemory>8</requiredMemory>
      <requiredNetworkBandwidth>7</requiredNetworkBandwidth>
    </CloudProcess>
    <CloudProcess id="342">
      <id>238</id>
      <requiredCpuPower>1</requiredCpuPower>
      <requiredMemory>9</requiredMemory>
      <requiredNetworkBandwidth>5</requiredNetworkBandwidth>
    </CloudProcess>
    <CloudProcess id="343">
      <id>239</id>
      <requiredCpuPower>6</requiredCpuPower>
      <requiredMemory>1</requiredMemory>
      <requiredNetworkBandwidth>1</requiredNetworkBandwidth>
    </CloudProcess>
    <CloudProcess id="344">
      <id>240</id>
      <requiredCpuPower>3</requiredCpuPower>
      <requiredMemory>13</requiredMemory>
      <requiredNetworkBandwidth>5</requiredNetworkBandwidth>
    </CloudProcess>
    <CloudProcess id="345">
      <id>241</id>
      <requiredCpuPower>1</requiredCpuPower>
      <requiredMemory>1</requiredMemory>
      <requiredNetworkBandwidth>1</requiredNetworkBandwidth>
    </CloudProcess>
    <CloudProcess id="346">
      <id>242</id>
      <requiredCpuPower>1</requiredCpuPower>
      <requiredMemory>1</requiredMemory>
      <requiredNetworkBandwidth>1</requiredNetworkBandwidth>
    </CloudProcess>
    <CloudProcess id="347">
      <id>243</id>
      <requiredCpuPower>1</requiredCpuPower>
      <requiredMemory>7</requiredMemory>
      <requiredNetworkBandwidth>1</requiredNetworkBandwidth>
    </CloudProcess>
    <CloudProcess id="348">
      <id>244</id>
      <requiredCpuPower>3</requiredCpuPower>
      <requiredMemory>16</requiredMemory>
      <requiredNetworkBandwidth>4</requiredNetworkBandwidth>
    </CloudProcess>
    <CloudProcess id="349">
      <id>245</id>
      <requiredCpuPower>1</requiredCpuPower>
      <requiredMemory>1</requiredMemory>
      <requiredNetworkBandwidth>1</requiredNetworkBandwidth>
    </CloudProcess>
    <CloudProcess id="350">
      <id>246</id>
      <requiredCpuPower>1</requiredCpuPower>
      <requiredMemory>1</requiredMemory>
      <requiredNetworkBandwidth>1</requiredNetworkBandwidth>
    </CloudProcess>
    <CloudProcess id="351">
      <id>247</id>
      <requiredCpuPower>1</requiredCpuPower>
      <requiredMemory>1</requiredMemory>
      <requiredNetworkBandwidth>1</requiredNetworkBandwidth>
    </CloudProcess>
    <CloudProcess id="352">
      <id>248</id>
      <requiredCpuPower>1</requiredCpuPower>
      <requiredMemory>1</requiredMemory>
      <requiredNetworkBandwidth>1</requiredNetworkBandwidth>
    </CloudProcess>
    <CloudProcess id="353">
      <id>249</id>
      <requiredCpuPower>9</requiredCpuPower>
      <requiredMemory>1</requiredMemory>
      <requiredNetworkBandwidth>1</requiredNetworkBandwidth>
    </CloudProcess>
    <CloudProcess id="354">
      <id>250</id>
      <requiredCpuPower>1</requiredCpuPower>
      <requiredMemory>2</requiredMemory>
      <requiredNetworkBandwidth>6</requiredNetworkBandwidth>
    </CloudProcess>
    <CloudProcess id="355">
      <id>251</id>
      <requiredCpuPower>3</requiredCpuPower>
      <requiredMemory>1</requiredMemory>
      <requiredNetworkBandwidth>1</requiredNetworkBandwidth>
    </CloudProcess>
    <CloudProcess id="356">
      <id>252</id>
      <requiredCpuPower>1</requiredCpuPower>
      <requiredMemory>1</requiredMemory>
      <requiredNetworkBandwidth>1</requiredNetworkBandwidth>
    </CloudProcess>
    <CloudProcess id="357">
      <id>253</id>
      <requiredCpuPower>6</requiredCpuPower>
      <requiredMemory>1</requiredMemory>
      <requiredNetworkBandwidth>1</requiredNetworkBandwidth>
    </CloudProcess>
    <CloudProcess id="358">
      <id>254</id>
      <requiredCpuPower>6</requiredCpuPower>
      <requiredMemory>1</requiredMemory>
      <requiredNetworkBandwidth>9</requiredNetworkBandwidth>
    </CloudProcess>
    <CloudProcess id="359">
      <id>255</id>
      <requiredCpuPower>1</requiredCpuPower>
      <requiredMemory>1</requiredMemory>
      <requiredNetworkBandwidth>2</requiredNetworkBandwidth>
    </CloudProcess>
    <CloudProcess id="360">
      <id>256</id>
      <requiredCpuPower>3</requiredCpuPower>
      <requiredMemory>4</requiredMemory>
      <requiredNetworkBandwidth>1</requiredNetworkBandwidth>
    </CloudProcess>
    <CloudProcess id="361">
      <id>257</id>
      <requiredCpuPower>3</requiredCpuPower>
      <requiredMemory>19</requiredMemory>
      <requiredNetworkBandwidth>5</requiredNetworkBandwidth>
    </CloudProcess>
    <CloudProcess id="362">
      <id>258</id>
      <requiredCpuPower>1</requiredCpuPower>
      <requiredMemory>2</requiredMemory>
      <requiredNetworkBandwidth>1</requiredNetworkBandwidth>
    </CloudProcess>
    <CloudProcess id="363">
      <id>259</id>
      <requiredCpuPower>1</requiredCpuPower>
      <requiredMemory>1</requiredMemory>
      <requiredNetworkBandwidth>6</requiredNetworkBandwidth>
    </CloudProcess>
    <CloudProcess id="364">
      <id>260</id>
      <requiredCpuPower>1</requiredCpuPower>
      <requiredMemory>1</requiredMemory>
      <requiredNetworkBandwidth>1</requiredNetworkBandwidth>
    </CloudProcess>
    <CloudProcess id="365">
      <id>261</id>
      <requiredCpuPower>1</requiredCpuPower>
      <requiredMemory>1</requiredMemory>
      <requiredNetworkBandwidth>2</requiredNetworkBandwidth>
    </CloudProcess>
    <CloudProcess id="366">
      <id>262</id>
      <requiredCpuPower>4</requiredCpuPower>
      <requiredMemory>1</requiredMemory>
      <requiredNetworkBandwidth>2</requiredNetworkBandwidth>
    </CloudProcess>
    <CloudProcess id="367">
      <id>263</id>
      <requiredCpuPower>6</requiredCpuPower>
      <requiredMemory>1</requiredMemory>
      <requiredNetworkBandwidth>3</requiredNetworkBandwidth>
    </CloudProcess>
    <CloudProcess id="368">
      <id>264</id>
      <requiredCpuPower>3</requiredCpuPower>
      <requiredMemory>20</requiredMemory>
      <requiredNetworkBandwidth>1</requiredNetworkBandwidth>
    </CloudProcess>
    <CloudProcess id="369">
      <id>265</id>
      <requiredCpuPower>1</requiredCpuPower>
      <requiredMemory>1</requiredMemory>
      <requiredNetworkBandwidth>2</requiredNetworkBandwidth>
    </CloudProcess>
    <CloudProcess id="370">
      <id>266</id>
      <requiredCpuPower>1</requiredCpuPower>
      <requiredMemory>2</requiredMemory>
      <requiredNetworkBandwidth>1</requiredNetworkBandwidth>
    </CloudProcess>
    <CloudProcess id="371">
      <id>267</id>
      <requiredCpuPower>2</requiredCpuPower>
      <requiredMemory>3</requiredMemory>
      <requiredNetworkBandwidth>3</requiredNetworkBandwidth>
    </CloudProcess>
    <CloudProcess id="372">
      <id>268</id>
      <requiredCpuPower>2</requiredCpuPower>
      <requiredMemory>1</requiredMemory>
      <requiredNetworkBandwidth>5</requiredNetworkBandwidth>
    </CloudProcess>
    <CloudProcess id="373">
      <id>269</id>
      <requiredCpuPower>1</requiredCpuPower>
      <requiredMemory>21</requiredMemory>
      <requiredNetworkBandwidth>2</requiredNetworkBandwidth>
    </CloudProcess>
    <CloudProcess id="374">
      <id>270</id>
      <requiredCpuPower>1</requiredCpuPower>
      <requiredMemory>1</requiredMemory>
      <requiredNetworkBandwidth>2</requiredNetworkBandwidth>
    </CloudProcess>
    <CloudProcess id="375">
      <id>271</id>
      <requiredCpuPower>1</requiredCpuPower>
      <requiredMemory>1</requiredMemory>
      <requiredNetworkBandwidth>1</requiredNetworkBandwidth>
    </CloudProcess>
    <CloudProcess id="376">
      <id>272</id>
      <requiredCpuPower>1</requiredCpuPower>
      <requiredMemory>1</requiredMemory>
      <requiredNetworkBandwidth>1</requiredNetworkBandwidth>
    </CloudProcess>
    <CloudProcess id="377">
      <id>273</id>
      <requiredCpuPower>1</requiredCpuPower>
      <requiredMemory>2</requiredMemory>
      <requiredNetworkBandwidth>1</requiredNetworkBandwidth>
    </CloudProcess>
    <CloudProcess id="378">
      <id>274</id>
      <requiredCpuPower>2</requiredCpuPower>
      <requiredMemory>12</requiredMemory>
      <requiredNetworkBandwidth>1</requiredNetworkBandwidth>
    </CloudProcess>
    <CloudProcess id="379">
      <id>275</id>
      <requiredCpuPower>7</requiredCpuPower>
      <requiredMemory>1</requiredMemory>
      <requiredNetworkBandwidth>1</requiredNetworkBandwidth>
    </CloudProcess>
    <CloudProcess id="380">
      <id>276</id>
      <requiredCpuPower>1</requiredCpuPower>
      <requiredMemory>1</requiredMemory>
      <requiredNetworkBandwidth>1</requiredNetworkBandwidth>
    </CloudProcess>
    <CloudProcess id="381">
      <id>277</id>
      <requiredCpuPower>1</requiredCpuPower>
      <requiredMemory>1</requiredMemory>
      <requiredNetworkBandwidth>1</requiredNetworkBandwidth>
    </CloudProcess>
    <CloudProcess id="382">
      <id>278</id>
      <requiredCpuPower>1</requiredCpuPower>
      <requiredMemory>1</requiredMemory>
      <requiredNetworkBandwidth>3</requiredNetworkBandwidth>
    </CloudProcess>
    <CloudProcess id="383">
      <id>279</id>
      <requiredCpuPower>1</requiredCpuPower>
      <requiredMemory>3</requiredMemory>
      <requiredNetworkBandwidth>1</requiredNetworkBandwidth>
    </CloudProcess>
    <CloudProcess id="384">
      <id>280</id>
      <requiredCpuPower>5</requiredCpuPower>
      <requiredMemory>1</requiredMemory>
      <requiredNetworkBandwidth>1</requiredNetworkBandwidth>
    </CloudProcess>
    <CloudProcess id="385">
      <id>281</id>
      <requiredCpuPower>1</requiredCpuPower>
      <requiredMemory>12</requiredMemory>
      <requiredNetworkBandwidth>1</requiredNetworkBandwidth>
    </CloudProcess>
    <CloudProcess id="386">
      <id>282</id>
      <requiredCpuPower>1</requiredCpuPower>
      <requiredMemory>1</requiredMemory>
      <requiredNetworkBandwidth>1</requiredNetworkBandwidth>
    </CloudProcess>
    <CloudProcess id="387">
      <id>283</id>
      <requiredCpuPower>1</requiredCpuPower>
      <requiredMemory>1</requiredMemory>
      <requiredNetworkBandwidth>8</requiredNetworkBandwidth>
    </CloudProcess>
    <CloudProcess id="388">
      <id>284</id>
      <requiredCpuPower>1</requiredCpuPower>
      <requiredMemory>10</requiredMemory>
      <requiredNetworkBandwidth>6</requiredNetworkBandwidth>
    </CloudProcess>
    <CloudProcess id="389">
      <id>285</id>
      <requiredCpuPower>1</requiredCpuPower>
      <requiredMemory>1</requiredMemory>
      <requiredNetworkBandwidth>1</requiredNetworkBandwidth>
    </CloudProcess>
    <CloudProcess id="390">
      <id>286</id>
      <requiredCpuPower>3</requiredCpuPower>
      <requiredMemory>5</requiredMemory>
      <requiredNetworkBandwidth>1</requiredNetworkBandwidth>
    </CloudProcess>
    <CloudProcess id="391">
      <id>287</id>
      <requiredCpuPower>1</requiredCpuPower>
      <requiredMemory>3</requiredMemory>
      <requiredNetworkBandwidth>1</requiredNetworkBandwidth>
    </CloudProcess>
    <CloudProcess id="392">
      <id>288</id>
      <requiredCpuPower>2</requiredCpuPower>
      <requiredMemory>2</requiredMemory>
      <requiredNetworkBandwidth>6</requiredNetworkBandwidth>
    </CloudProcess>
    <CloudProcess id="393">
      <id>289</id>
      <requiredCpuPower>5</requiredCpuPower>
      <requiredMemory>2</requiredMemory>
      <requiredNetworkBandwidth>1</requiredNetworkBandwidth>
    </CloudProcess>
    <CloudProcess id="394">
      <id>290</id>
      <requiredCpuPower>1</requiredCpuPower>
      <requiredMemory>1</requiredMemory>
      <requiredNetworkBandwidth>3</requiredNetworkBandwidth>
    </CloudProcess>
    <CloudProcess id="395">
      <id>291</id>
      <requiredCpuPower>1</requiredCpuPower>
      <requiredMemory>1</requiredMemory>
      <requiredNetworkBandwidth>1</requiredNetworkBandwidth>
    </CloudProcess>
    <CloudProcess id="396">
      <id>292</id>
      <requiredCpuPower>5</requiredCpuPower>
      <requiredMemory>4</requiredMemory>
      <requiredNetworkBandwidth>1</requiredNetworkBandwidth>
    </CloudProcess>
    <CloudProcess id="397">
      <id>293</id>
      <requiredCpuPower>1</requiredCpuPower>
      <requiredMemory>1</requiredMemory>
      <requiredNetworkBandwidth>2</requiredNetworkBandwidth>
    </CloudProcess>
    <CloudProcess id="398">
      <id>294</id>
      <requiredCpuPower>1</requiredCpuPower>
      <requiredMemory>2</requiredMemory>
      <requiredNetworkBandwidth>1</requiredNetworkBandwidth>
    </CloudProcess>
    <CloudProcess id="399">
      <id>295</id>
      <requiredCpuPower>1</requiredCpuPower>
      <requiredMemory>5</requiredMemory>
      <requiredNetworkBandwidth>4</requiredNetworkBandwidth>
    </CloudProcess>
    <CloudProcess id="400">
      <id>296</id>
      <requiredCpuPower>1</requiredCpuPower>
      <requiredMemory>2</requiredMemory>
      <requiredNetworkBandwidth>1</requiredNetworkBandwidth>
    </CloudProcess>
    <CloudProcess id="401">
      <id>297</id>
      <requiredCpuPower>10</requiredCpuPower>
      <requiredMemory>3</requiredMemory>
      <requiredNetworkBandwidth>2</requiredNetworkBandwidth>
    </CloudProcess>
    <CloudProcess id="402">
      <id>298</id>
      <requiredCpuPower>1</requiredCpuPower>
      <requiredMemory>1</requiredMemory>
      <requiredNetworkBandwidth>12</requiredNetworkBandwidth>
    </CloudProcess>
    <CloudProcess id="403">
      <id>299</id>
      <requiredCpuPower>1</requiredCpuPower>
      <requiredMemory>31</requiredMemory>
      <requiredNetworkBandwidth>1</requiredNetworkBandwidth>
    </CloudProcess>
  </processList>
</CloudBalance>